{"erDataList":[{"name":"新和县供销联社排先巴扎供销社","code":"916529259297916305","registrationDay":"1989-01-14","character":"集体分支机构(非法人)","legalRepresentative":"阿拉吾西·依米提","capital":"N/A","businessScope":"许可经营项目：农药；代销民乐、美丰农作物包装种子。一般经营项目：化肥、地膜、小农具、滴灌带零售；房屋租赁服务。","province":"新疆","city":"阿克苏","address":"新疆阿克苏地区新和县排先巴扎乡"},{"name":"察布查尔锡伯自治县供销社贸易总公司","code":"916540227108529968","registrationDay":"1989-01-16","character":"集体所有制","legalRepresentative":"何华","capital":"125万人民币","businessScope":"农药，化肥，地膜，畜产品，农副产品，包装种子，房屋租赁，棉花购销,日用百货,农牧林机械，仪器设备，种植养殖，技术咨询服务。","province":"新疆","city":"伊犁哈萨克","address":"新疆伊犁州察布查尔县查鲁盖西街"},{"name":"疏附县供销社塔什米力克加油站","code":"91653121742214075W","registrationDay":"1989-01-17","character":"集体分支机构(非法人)","legalRepresentative":"阿卜杜热西提·托合提","capital":"N/A","businessScope":"许可经营项目：成品油销售","province":"新疆","city":"喀什","address":"新疆喀什地区疏附县塔什米力克乡供销社（塔什米力克乡7村）"},{"name":"疏附县农村信用合作联社萨依巴格信用社","code":"916531217108258088","registrationDay":"1989-01-21","character":"N/A","legalRepresentative":"阿布都热衣木江·多力坤","capital":"N/A","businessScope":"办理存款、货款、票据贴现、国内结算业务、办理个人储蓄业务、代理收付款项及受托代办保险业务、买卖政府债劵、代理发行、代理兑付、承销政府债劵、提供保险箱服务、由县联社統一办理资金融通调剂业务、办理经中国银行监督管理委员会批准的其他业务","province":"新疆","city":"喀什","address":"新疆喀什地区疏附县萨依巴格乡"},{"name":"疏附县农村信用合作联社塔什米力克信用社","code":"91653121710825859G","registrationDay":"1989-01-21","character":"N/A","legalRepresentative":"木太力普·苏然","capital":"N/A","businessScope":"许可经营项目：办理存款、货款、票据贴现、国内结算业务、办理个人储蓄业务、代理收付款项及受托代办保险业务、买卖政府债劵、代理发行、代理兑付、承销政府债劵、提供保险箱服务、由县联社統一办理资金融通调剂业务、办理经中国银行监督管理委员会批准的其他业务","province":"新疆","city":"喀什","address":"新疆喀什地区疏附县塔什米力克乡"},{"name":"额敏县农村信用合作联社额玛勒郭楞信用社","code":"9165422171086185X2","registrationDay":"1989-01-23","character":"N/A","legalRepresentative":"刘新娟","capital":"N/A","businessScope":"许可该机构经营中国银行业监督管理委员会、依照有关法律、行政法规和其它规定批准的业务、经营范围以批准文件所列的为准。","province":"新疆","city":"塔城","address":"新疆塔城地区额敏县额玛勒郭楞蒙古乡"},{"name":"额敏县农村信用合作联社霍吉尔特信用社","code":"91654221710861876W","registrationDay":"1989-01-23","character":"N/A","legalRepresentative":"薛焕成","capital":"N/A","businessScope":"许可该机构经营中国银行业监督管理委员会、依照有关法律、行政法规和其它规定批准的业务、经营范围以批准文件所列的为准。","province":"新疆","city":"塔城","address":"新疆塔城地区额敏县霍吉尔特乡"},{"name":"叶城县农村信用合作联社","code":"916531262301607470","registrationDay":"1989-02-01","character":"N/A","legalRepresentative":"温且姆·图尔荪","capital":"7,239(万)","businessScope":"许可经营项目：许可该机构经营中国银行业监督管理委员会依照有关法律、法规和其他规定的业务，经营范围以批准文件所列的为准。。一般经营项目：无。","province":"新疆","city":"喀什","address":"新疆喀什地区叶城县新城南路"},{"name":"吉木萨尔县大有供销合作社","code":"916523272293401501","registrationDay":"1989-02-15","character":"集体所有制","legalRepresentative":"何福寿","capital":"54万人民币","businessScope":"农药零售（剧毒品和国家明令禁止销售的除外）；销售不再分装的包装种子，化肥零售，喷雾器及其配件的零售，农副产品购销","province":"新疆","city":"昌吉","address":"新疆昌吉州吉木萨尔县大有乡街"},{"name":"新疆天利石化控股集团有限公司","code":"916502027107581077","registrationDay":"1989-02-20","character":"N/A","legalRepresentative":"徐文清","capital":"14,000(万)","businessScope":"植物油加工和销售,普通货物运输服务；甲苯、易燃液体：苯、二甲苯异构体混合物、石脑油销售；苯乙烯、异戊二烯、双环戊二烯、正戊烷、异戊烷、环戊烷、间戊二烯、混合二甲苯、混合三甲苯、混合四甲苯、工业用裂解碳九（一等品）、工业用裂解碳九（合格品）、混合重组分油、混合甲基萘、石油萘、重芳烃、盐酸的生产及销售；石化产品的生产和销售、原材料、石化机械及运输设备配件销售，房屋租赁，国内商业、木器制作零售，经营本企业及成员企业自产产品和技术的进出口业务、仪器仪表、机械设备（发电机、打磨机、切割机、砂轮机、电焊机除外）、零配件及技术的进出口业务","province":"新疆","city":"克拉玛依","address":"新疆克拉玛依市独山子区南海路15号"},{"name":"麦盖提县希依提墩供销合作社","code":"91653127230180115J","registrationDay":"1989-03-05","character":"集体所有制","legalRepresentative":"艾买尔·艾合买提","capital":"181万人民币","businessScope":"花肥、地摸、农机、塑料制品、橡胶制品；五金、有机无机复合肥、房屋租赁服务。","province":"新疆","city":"喀什","address":"新疆喀什地区麦盖提县希依提墩乡"},{"name":"英吉沙县龙甫供销社","code":"91653123230100621U","registrationDay":"1989-03-08","character":"集体所有制","legalRepresentative":"亥热提·麦麦提","capital":"19万人民币","businessScope":"许可经营项目：无。一般经营项目：化肥、地膜的销售。","province":"新疆","city":"喀什","address":"新疆喀什地区英吉沙县龙甫乡"},{"name":"叶城县夏合甫供销合作社","code":"91653126230160157Y","registrationDay":"1989-03-09","character":"集体所有制","legalRepresentative":"艾买尔艾力·阿布都拉","capital":"75万人民币","businessScope":"化肥、农用地膜、建材、农用机械零售，房屋租赁。","province":"新疆","city":"喀什","address":"新疆喀什地区叶城县夏合甫乡"},{"name":"叶城县佰西热克供销合作社","code":"91653126230160165R","registrationDay":"1989-03-09","character":"集体所有制","legalRepresentative":"吐鲁洪·沙依提","capital":"30万人民币","businessScope":"化肥、地膜、屋屋出租、农副土特产品、日用百货、针纺织品、五金、建材、农用机械。","province":"新疆","city":"喀什","address":"新疆叶城县叶城县佰西热克乡"},{"name":"叶城县依提木孔供销合作社","code":"91653126230160122C","registrationDay":"1989-03-10","character":"集体所有制","legalRepresentative":"吐尔孙江·吐鲁甫","capital":"50万人民币","businessScope":"许可经营项目：无。一般经营项目：","province":"新疆","city":"喀什","address":"叶城县依提木孔乡"},{"name":"英吉沙县乔日旁供销社","code":"916531232301006131","registrationDay":"1989-03-10","character":"集体所有制","legalRepresentative":"色麦提.吾布力","capital":"25万人民币","businessScope":"许可经营项目：无。一般经营项目：(国家法律、行政法规有专项审批的项目除外)：化肥、地膜、日用百货、针纺织品。","province":"新疆","city":"喀什","address":"新疆喀什地区英吉沙县乔尔旁乡"},{"name":"英吉沙县芒辛乡供销社","code":"91653123MA77M1A964","registrationDay":"1989-03-10","character":"集体所有制","legalRepresentative":"阿卜赛塔尔·艾散","capital":"32万人民币","businessScope":"许可经营项目：无。一般经营项目：(国家法律、行政法规有专项审批的项目除外)：化肥、地膜销售，小五金,棉纺织品零售。","province":"新疆","city":"喀什","address":"英吉沙县芒辛乡"},{"name":"叶城县江格勒斯供销合作社","code":"916531262301601494","registrationDay":"1989-03-12","character":"集体所有制","legalRepresentative":"马木提麦合木提","capital":"35万人民币","businessScope":"化肥、农用地膜、干鲜果品、建材、农用机械及配件销售。","province":"新疆","city":"喀什","address":"新疆喀什地区叶城县江格勒斯乡8村"},{"name":"伊犁金粱子粮业加工厂","code":"91654023230612109G","registrationDay":"1989-03-13","character":"N/A","legalRepresentative":"张玉杰","capital":"120(万元人民币)","businessScope":"粮食收购，销售，粮油代加工。","province":"新疆","city":"伊犁哈萨克","address":"新疆伊犁州霍城县六十六团团部幸福路"},{"name":"察布查尔县农村信用合作联社","code":"91654022715564627G","registrationDay":"1989-03-15","character":"N/A","legalRepresentative":"章文宝","capital":"N/A","businessScope":"经营中国银行业监督管理委员会依照有关法律、行政法规和其他规定批准的业务，经营范围以批准文件所列的为准。","province":"新疆","city":"伊犁哈萨克","address":"新疆伊犁州察布查尔县城镇查鲁盖东街"},{"name":"察布查尔县农村信用合作联社绰霍尔信用社","code":"91654022328856902M","registrationDay":"1989-03-15","character":"N/A","legalRepresentative":"章文宝","capital":"N/A","businessScope":"经营中国银行业监督管理委员会依照有关法律、行政法规和其他规定批准的业务，经营范围以批准文件所列的为准。","province":"新疆","city":"伊犁哈萨克","address":"新疆伊犁察布查尔县绰霍尔乡"},{"name":"吉木萨尔县泉子街供销社","code":"91652327229340425E","registrationDay":"1989-03-15","character":"集体所有制","legalRepresentative":"刘生虎","capital":"41.6万人民币","businessScope":"（具体经营项目以有关部门颁发的资质证书、许可证书为准）农药零售（剧毒品和国家明令禁止销售的除外）（许可证有效期限至2012年10月25日）（国家法律、行政法规有专项审批的项目除外）：批发零售百货、针纺织品、五金；零售建筑材料、化工、交电、中小农具、化肥、农膜、喷雾器及其配件、不再分装的包装种子；...","province":"新疆","city":"昌吉","address":"新疆昌吉州吉木萨尔县泉子街镇"},{"name":"叶城县轻工集体经济联社供销公司","code":"91653126230160173L","registrationDay":"1989-03-16","character":"集体所有制","legalRepresentative":"努尔艾合买提·吐鲁甫","capital":"3万人民币","businessScope":"住宿，针纺织品、日用杂品、五金交电、家用电器、水暖配件、停车服务。","province":"新疆","city":"喀什","address":"新疆喀什地区叶城县文化路"},{"name":"木垒哈萨克自治县农村信用合作联社","code":"91652328929360398N","registrationDay":"1989-03-17","character":"N/A","legalRepresentative":"朱智岗","capital":"16,499.5353(万元人民币)","businessScope":"许可经营项目：办理存款、贷款；票据贴现、国内结算业务；办理个人储蓄业务；代理其他银行的金融业务；代理收付项及受托代办保险业务；买卖政府债券；代理发行；代理电讯业务；代理兑现、承销政府债券；提供保险箱服务；由县联社统一办理资金融通调剂业务，办理经中国银行业监督管理委员会批准的其他业务。#。一般经营项目：无。","province":"新疆","city":"昌吉","address":"新疆昌吉州木垒县北环东路55号"},{"name":"阿瓦提县唐木托拉克乡供销合作社","code":"91652928229850425G","registrationDay":"1989-03-18","character":"集体所有制","legalRepresentative":"木沙江·艾山","capital":"135.73万人民币","businessScope":"化肥、地膜、百货、五金交电、农副产品销售，房屋租赁","province":"新疆","city":"阿克苏","address":"新疆阿克苏地区阿瓦提县唐木吐拉克乡"},{"name":"沙雅县农村信用合作联社","code":"916529242297703968","registrationDay":"1989-03-22","character":"N/A","legalRepresentative":"刘志勇","capital":"12,569(万)","businessScope":"许可经营项目：金融业务。 一般经营项目：无。","province":"新疆","city":"阿克苏","address":"新疆阿克苏地区沙雅县人民南路2号"},{"name":"伽师县夏普吐勒乡供销社","code":"91653129726961548T","registrationDay":"1989-03-22","character":"集体所有制","legalRepresentative":"阿卜杜热西提·阿卜拉","capital":"60万人民币","businessScope":"化肥(硝基复混肥除外）、地膜、五金、日用百货、预包装食品、散装食品、粮油、副食品的销售；房屋租赁、商务咨询服务、电子商务、网络营销；农业种植；农副产品线上线下产品推广与销售。","province":"新疆","city":"喀什","address":"新疆喀什地区伽师县夏普吐勒乡"},{"name":"博乐市贝林哈日莫墩乡供销社","code":"91652701229401400N","registrationDay":"1989-03-23","character":"集体所有制","legalRepresentative":"贺文全","capital":"52万人民币","businessScope":"有毒品（农药）批发、零售","province":"新疆","city":"博尔塔拉","address":"新疆博州博乐市贝林哈日莫墩乡"},{"name":"和硕县供销合作总公司","code":"91652828229641295H","registrationDay":"1989-03-23","character":"集体所有制","legalRepresentative":"王超","capital":"2100万人民币","businessScope":"农业生产资料，农副产品，五金化工（管制器具除外），建材，土特产，养殖业，种植业，房屋租赁，土地租赁","province":"新疆","city":"巴音郭楞","address":"新疆巴州和硕县解放北路"},{"name":"新和县供销联社生产资料公司连锁10分店","code":"91652925773495244F","registrationDay":"1989-03-24","character":"集体分支机构(非法人)","legalRepresentative":"魏勇","capital":"N/A","businessScope":"许可经营项目：农药。一般经营项目：化肥、农用地膜、小农具、滴灌带销售。","province":"新疆","city":"阿克苏","address":"新疆阿克苏地区新和县乌喀路（三角地）"},{"name":"英吉沙县色提力供销社","code":"916531237576953269","registrationDay":"1989-03-24","character":"集体所有制","legalRepresentative":"亥热古丽乌斯曼","capital":"16万人民币","businessScope":"许可经营项目：无。一般经营项目：(国家法律、行政法规有专项审批的项目除外)：地膜、化肥的零售，干鲜果品加工，房屋租赁。","province":"新疆","city":"喀什","address":"新疆喀什地区英吉沙县色提力乡"},{"name":"英吉沙县乌恰乡供销社","code":"91653123MA77M1C80U","registrationDay":"1989-03-27","character":"集体所有制","legalRepresentative":"安尼瓦尔木萨","capital":"58万人民币","businessScope":"许可经营项目：无。一般经营项目：化肥、地膜的零售；五金交电、日用品零售；杏子收购与销售；房屋租赁。","province":"新疆","city":"喀什","address":"英吉沙县乌恰乡"},{"name":"轮台县供销合作社联合社农业生产资料公司","code":"91652822229520370M","registrationDay":"1989-03-28","character":"集体所有制","legalRepresentative":"赵琦","capital":"82万人民币","businessScope":"零售：农药（剧毒农药除外）；烟花B级、C级、D级；爆竹B级、C级；种子","province":"新疆","city":"巴音郭楞","address":"新疆巴州轮台县波斯坦路"},{"name":"轮台县供销合作社联合社棉麻公司","code":"91652822229520135M","registrationDay":"1989-03-28","character":"集体所有制","legalRepresentative":"陈道金","capital":"1259万人民币","businessScope":"皮棉、棉籽、棉短绒、土特产、日用百货、五金交电、服装鞋帽、针纺织品、其他日用品、牛羊育肥销售；种植、养殖。","province":"新疆","city":"巴音郭楞","address":"新疆巴州轮台县团结路"},{"name":"轮台县供销合作社联合社茶畜公司","code":"91652822229520389J","registrationDay":"1989-03-28","character":"集体所有制","legalRepresentative":"哈斯木·买买提","capital":"54万人民币","businessScope":"预包装食品零售；皮毛收购、加工销售；牲畜的饲养；房屋租赁*。","province":"新疆","city":"巴音郭楞","address":"新疆巴州轮台县波斯坦路"},{"name":"莎车县托木吾斯塘乡供销社","code":"91653125230141247W","registrationDay":"1989-03-30","character":"集体所有制","legalRepresentative":"塞皮丁·麦麦提","capital":"59.3万人民币","businessScope":"许可经营项目：无。一般经营项目：一般经营项目","province":"新疆","city":"喀什","address":"新疆喀什地区莎车县托木吾斯塘乡"},{"name":"阿瓦提县英艾日克乡供销合作社","code":"916529282298504416","registrationDay":"1989-03-30","character":"集体所有制","legalRepresentative":"阿不都热扎克·吐尼牙孜","capital":"182万人民币","businessScope":"化学肥料、地膜、针纺织品，五金交电、农用机械销售，房屋租赁","province":"新疆","city":"阿克苏","address":"新疆阿克苏地区阿瓦提县英艾日克乡"},{"name":"莎车县艾力西湖供销社","code":"91653125230141271D","registrationDay":"1989-03-31","character":"集体所有制","legalRepresentative":"塔依尔·艾山","capital":"88.5万人民币","businessScope":"许可经营项目：许可经营项目（具体经营项目以有关部门批准文件或颁发的许可证、资质证书为准）：无。一般经营项目：一般经营项目（国家法律、行政法规有专项审批的项目除外）：化肥、农用薄膜、家用电器、五金、建材","province":"新疆","city":"喀什","address":"新疆喀什地区莎车县艾力西湖镇"},{"name":"莎车县阿斯兰巴格乡供销社","code":"916531252301412392","registrationDay":"1989-04-01","character":"集体所有制","legalRepresentative":"吐尔孙江·托合提","capital":"81.8万人民币","businessScope":"许可经营项目：许可经营项目","province":"新疆","city":"喀什","address":"新疆喀什地区莎车县阿斯兰巴格乡"},{"name":"莎车县阿斯兰巴格乡供销社第十门市部","code":"91653125798174391Q","registrationDay":"1989-04-01","character":"集体分支机构(非法人)","legalRepresentative":"阿布都热希提·吐合提","capital":"N/A","businessScope":"化肥，农用薄膜、农副产品","province":"新疆","city":"喀什","address":"新疆喀什地区莎车县阿斯兰巴格乡"},{"name":"麦盖提县央塔克供销合作社","code":"916531272301802549","registrationDay":"1989-04-02","character":"集体所有制","legalRepresentative":"吐逊·艾合买提","capital":"120万人民币","businessScope":"有机无机复合肥、中小农具、养殖业、种植业、土特产品、须产品、非生产性废旧物资回收、市场开办、房屋（摊位）出租、工业品、百货、日用品、建筑材料、农副产品收购；","province":"新疆","city":"喀什","address":"新疆喀什地区麦盖提县央塔克乡"},{"name":"莎车县艾力西湖供销社第十六门市部","code":"916531257981758619","registrationDay":"1989-04-03","character":"集体分支机构(非法人)","legalRepresentative":"吐尔迪·库尔班","capital":"N/A","businessScope":"化肥、农用薄膜、农副产品","province":"新疆","city":"喀什","address":"新疆喀什地区莎车县阔什艾热克乡"},{"name":"英吉沙县英也尔供销社","code":"916531232301006649","registrationDay":"1989-04-05","character":"集体所有制","legalRepresentative":"达吾提·艾萨","capital":"11万人民币","businessScope":"化肥(硝基复混肥除外)、地膜、百货，纺织品，日用杂品。","province":"新疆","city":"喀什","address":"英吉沙县英也尔乡"},{"name":"莎车县依什库力乡供销社","code":"91653125230141212A","registrationDay":"1989-04-07","character":"集体所有制","legalRepresentative":"伊盖木拜尔迪·马木提","capital":"125.9万人民币","businessScope":"销售：预包装食品兼散装食品（保健食品除外），化肥、农用薄膜、农副产品、日用百货、纺织品、针织品、五金、建材","province":"新疆","city":"喀什","address":"新疆喀什地区莎车县伊什库力乡"},{"name":"伽师县巴仁镇供销社","code":"91653129726961556M","registrationDay":"1989-04-08","character":"集体所有制","legalRepresentative":"蒋二昌","capital":"63万人民币","businessScope":"化肥(硝基复混肥除外)，地膜、房屋租赁、农业种植、农副产品线上线下产品推广与销售、商务咨询服务、货物配送、电子商务、网络营销、预包装食品、散装食品、日用百货、五金交电的销售。","province":"新疆","city":"喀什","address":"新疆喀什地区伽师县古宰尔东路13号"},{"name":"库车县供销社玉奇吾斯塘基层社","code":"91652923229750520U","registrationDay":"1989-04-08","character":"集体所有制","legalRepresentative":"吐尔逊·库尔班","capital":"16.4万人民币","businessScope":"农药，各类农作物种子；化肥，地膜，水泥,石灰,居民生活用煤零售,房屋出租。","province":"新疆","city":"阿克苏","address":"新疆阿克苏地区库车县玉奇吾斯塘乡"},{"name":"伽师县克孜勒博依镇供销社","code":"916531297189922723","registrationDay":"1989-04-10","character":"集体所有制","legalRepresentative":"艾力·图尔逊","capital":"96万人民币","businessScope":"化肥(硝基复混肥除外）、地膜、五金、日用百货、预包装食品、散装食品、粮油、副食品的销售；房屋租赁、商务咨询服务、电子商务、网络营销；农业种植；农副产品线上线下产品推广与销售。","province":"新疆","city":"喀什","address":"新疆喀什地区伽师县克孜勒博依镇"},{"name":"新疆塔什库尔干塔吉克自治县第一区供销社","code":"91653131230260051G","registrationDay":"1989-04-10","character":"集体所有制","legalRepresentative":"热合曼·艾山胡江","capital":"79万人民币","businessScope":"土产、畜产品收购与销售、布、服装、日用百货、鞋帽、毛线、各种型号油桶","province":"新疆","city":"喀什","address":"新疆喀什地区塔什库尔干县塔什库尔干西路"},{"name":"莎车县恰热克供销社第十门市部","code":"91653125798189278J","registrationDay":"1989-04-10","character":"集体分支机构(非法人)","legalRepresentative":"阿布都卡依尔·阿布都卡地尔","capital":"N/A","businessScope":"化肥、农用薄膜、建材（危化品除外）、农副产品","province":"新疆","city":"喀什","address":"新疆喀什地区莎车县恰热克镇库木齐提村"},{"name":"莎车县恰热克供销社第六门市部","code":"91653125798189251T","registrationDay":"1989-04-10","character":"集体分支机构(非法人)","legalRepresentative":"阿布都萨依提·吐合提","capital":"N/A","businessScope":"化肥、农用薄膜、建材（危化品除外）、农副产品","province":"新疆","city":"喀什","address":"新疆喀什地区莎车县恰热克镇巴扎村"},{"name":"莎车县恰热克镇供销社","code":"916531252301412985","registrationDay":"1989-04-10","character":"集体所有制","legalRepresentative":"阿布都艾尼·阿布都卡地尔","capital":"62.5万人民币","businessScope":"化肥、农副产品（粮棉除外）农用薄膜、建材","province":"新疆","city":"喀什","address":"新疆喀什地区莎车县恰热克镇"},{"name":"乌什县供销合作联合社阿恰塔格乡基层供销社","code":"91652927MA777BWLXF","registrationDay":"1989-04-11","character":"集体所有制","legalRepresentative":"程刚","capital":"25.4万人民币","businessScope":"许可经营项目：无。一般经营项目：农副产品，纺织，服装及日用品，茶叶，建筑用五金，文具用品，农具，化肥、农膜批发零售，房屋租赁，土地租赁。","province":"新疆","city":"阿克苏","address":"新疆阿克苏地区乌什县阿恰塔格乡"},{"name":"莎车县阿扎提巴格乡供销社","code":"9165312523014128X5","registrationDay":"1989-04-11","character":"集体所有制","legalRepresentative":"凯尤木·萨伍提","capital":"80.9万人民币","businessScope":"许可经营项目：（具体经营项目以有关部门批准文件或颁发的许可证、资质证书为准）：无。一般经营项目：","province":"新疆","city":"喀什","address":"莎车县阿扎提巴格乡卡力帕克吨村"},{"name":"乌什县供销合作联合社奥特贝希乡基层供销社","code":"91652927MA777BWP2Y","registrationDay":"1989-04-12","character":"集体所有制","legalRepresentative":"程刚","capital":"60.6万人民币","businessScope":"许可经营项目：无。一般经营项目：","province":"新疆","city":"阿克苏","address":"新疆阿克苏地区乌什县奥特贝希乡"},{"name":"新疆新筑路桥建设有限责任公司","code":"9165010922924197XR","registrationDay":"1989-04-12","character":"有限责任公司","legalRepresentative":"丁峰","capital":"5143万人民币","businessScope":"公路施工总承包及公路养护；公路交通工程施工；...机械制造及维修；汽车、工程机械及配件销售；金属复合网的生产及安装；金属制品的制造和销售；标线漆、钢材、汽车配件、橡胶制品、五金交电、工程机械电器、轴承的销售；机械设备租赁；物业管理；房屋出租；房屋建筑工程；市政工程；钢结构工程；劳务派遣；劳务分包。","province":"新疆","city":"乌鲁木齐","address":"新疆乌鲁木齐市米东南路4265号11栋"},{"name":"和静县牧工商联合公司","code":"91652827229620849M","registrationDay":"1989-04-12","character":"国有企业","legalRepresentative":"张湘梅","capital":"55万人民币","businessScope":"铁矿石、白云岩开采","province":"新疆","city":"巴音郭楞","address":"新疆巴州和静县和静镇查汗通沟西路"},{"name":"焉耆回族自治县永宁供销社","code":"916528262296025873","registrationDay":"1989-04-12","character":"集体所有制","legalRepresentative":"史彩萍","capital":"30万人民币","businessScope":"日用百货、针纺织品、五金交电、化工(危险品除外)、日用杂品、化肥、农膜、废旧物品、苇制品、畜产品。","province":"新疆","city":"巴音郭楞","address":"新疆巴州焉耆县永宁镇"},{"name":"叶城县乌夏巴什供销合作社","code":"91653126230160296M","registrationDay":"1989-04-12","character":"集体所有制","legalRepresentative":"吐尔洪·麦麦提孜","capital":"41万人民币","businessScope":"日用百货、日用杂品、五金、针纺织品、化肥、地膜、建材、农机、房屋出租。","province":"新疆","city":"喀什","address":"新疆喀什地区叶城县乌夏巴什镇"},{"name":"伽师县和夏瓦提乡供销社","code":"9165312972698028X7","registrationDay":"1989-04-12","character":"集体所有制","legalRepresentative":"张野","capital":"104万人民币","businessScope":"化肥(硝基复混肥除外）、地膜、五金、日用百货、预包装食品、散装食品、粮油、副食品的销售；房屋租赁、商务咨询服务、电子商务、网络营销；农业种植；农副产品线上线下产品推广与销售。","province":"新疆","city":"喀什","address":"新疆喀什地区伽师县和夏瓦提乡"},{"name":"莎车县塔尕其乡供销社","code":"91653125230141319M","registrationDay":"1989-04-13","character":"集体所有制","legalRepresentative":"阿布都赛买提·吐尔孙","capital":"85.1万人民币","businessScope":"化肥、农用薄膜、其他日用品、农副产品","province":"新疆","city":"喀什","address":"新疆喀什地区莎车县塔尕其乡"},{"name":"莎车县依干其供销社","code":"916531257981744391","registrationDay":"1989-04-13","character":"集体所有制","legalRepresentative":"阿迪力·赛麦尔","capital":"35万人民币","businessScope":"许可经营项目：许可经营项目","province":"新疆","city":"喀什","address":"莎车县依干其镇"},{"name":"莎车县佰什坎镇供销社","code":"91653125781752538P","registrationDay":"1989-04-13","character":"集体所有制","legalRepresentative":"阿布来提·吐尔迪","capital":"169万人民币","businessScope":"许可经营项目：无。一般经营项目：一般经营项目","province":"新疆","city":"喀什","address":"莎车县佰什坎镇"},{"name":"莎车县依干其供销社第二门市部","code":"916531257981744204","registrationDay":"1989-04-13","character":"集体分支机构(非法人)","legalRepresentative":"麦麦提·阿西木","capital":"N/A","businessScope":"化肥、农用薄膜、建材","province":"新疆","city":"喀什","address":"新疆喀什地区莎车县依干其镇"},{"name":"莎车县阿热勒乡供销社第一门市部","code":"91653125MA776UK16K","registrationDay":"1989-04-13","character":"集体分支机构(非法人)","legalRepresentative":"吐尔孙·马木提","capital":"N/A","businessScope":"化肥（硝基复混肥除外）、农用薄膜、建材","province":"新疆","city":"喀什","address":"新疆喀什地区莎车县恰热巴格乡巴扎内"},{"name":"叶城县加依提勒克供销合作社","code":"91653126230160288T","registrationDay":"1989-04-14","character":"集体所有制","legalRepresentative":"吐尔洪·麦麦提孜","capital":"48万人民币","businessScope":"化肥、地膜、针纺织品、日用百货、五金、土特产品、农机销售、房屋出租。","province":"新疆","city":"喀什","address":"新疆喀什地区叶城县加依提勒克乡"},{"name":"伽师县江巴孜乡供销社","code":"916531297269802987","registrationDay":"1989-04-14","character":"集体所有制","legalRepresentative":"喀斯木·库宛","capital":"61万人民币","businessScope":"化肥(硝基复混肥除外）、地膜、五金、日用百货、预包装食品、散装食品、粮油、副食品的销售；房屋租赁、商务咨询服务、电子商务、网络营销；农业种植；农副产品线上线下产品推广与销售。","province":"新疆","city":"喀什","address":"新疆喀什地区伽师县江巴孜乡"},{"name":"木垒哈萨克自治县农村信用合作联社市场信用社","code":"91652328MA777LD20E","registrationDay":"1989-04-14","character":"N/A","legalRepresentative":"郭春孝","capital":"N/A","businessScope":"许可经营项目：无。一般经营项目：经营许可证批准的范围#。","province":"新疆","city":"昌吉","address":"新疆昌吉州木垒县城农贸市场"},{"name":"莎车县卡群乡供销社","code":"91653125230141378Q","registrationDay":"1989-04-15","character":"集体所有制","legalRepresentative":"艾尔肯·霍加木尼亚孜","capital":"49.6万人民币","businessScope":"化肥、农用薄膜、针织品、农副产品","province":"新疆","city":"喀什","address":"新疆喀什地区莎车县卡群乡"},{"name":"察布查尔县农村信用合作联社孙扎齐牛录信用社","code":"9165402232885582XE","registrationDay":"1989-04-15","character":"N/A","legalRepresentative":"张华","capital":"N/A","businessScope":"经营中国银行业监督管理委员会依照有关法律、行政法规和其他规定批准的业务，经营范围以批准文件所列的为准。","province":"新疆","city":"伊犁哈萨克","address":"新疆伊犁察布查尔县孙扎齐牛录乡"},{"name":"莎车县阿热勒乡供销社","code":"9165312523014136XQ","registrationDay":"1989-04-15","character":"集体所有制","legalRepresentative":"玉斯普卡迪尔·巴热提","capital":"65.5万人民币","businessScope":"化肥(硝基复混肥除外)、农用薄膜、针织品、五金、家用电器、农副产品(粮棉除外）、房屋租赁；代销包装种子。","province":"新疆","city":"喀什","address":"新疆喀什地区莎车县阿热勒乡"},{"name":"察布查尔县农村信用合作联社扎格斯台信用社","code":"9165402232878446X9","registrationDay":"1989-04-15","character":"N/A","legalRepresentative":"夏甫哈提·斯德克江","capital":"N/A","businessScope":"经营中国银行业监督管理委员会依照有关法律、行政法规和其他规定批准的业务，经营范围以批准文件所列的为准。","province":"新疆","city":"伊犁哈萨克","address":"新疆伊犁察布查尔县扎格斯台乡"},{"name":"叶城县恰瓦克供销合作社","code":"916531262301602613","registrationDay":"1989-04-15","character":"集体所有制","legalRepresentative":"吐鲁洪·热合曼","capital":"59万人民币","businessScope":"化肥、农用地膜、农机配件、建筑用水泥、各种钢材及压延产品、五金、日用百货、针纺织品、农用机械。","province":"新疆","city":"喀什","address":"新疆喀什地区叶城县恰瓦克镇"},{"name":"察布查尔锡伯自治县扎格斯台乡供销社","code":"91654022MA77587D6N","registrationDay":"1989-04-15","character":"集体所有制","legalRepresentative":"胡林昌","capital":"15万人民币","businessScope":"化肥，地膜，农副产品购销，废品收购。","province":"新疆","city":"伊犁哈萨克","address":"新疆伊犁州察布查尔县扎克斯台乡"},{"name":"昭苏县农村信用合作联社夏塔信用社","code":"91654026710855978U","registrationDay":"1989-04-18","character":"N/A","legalRepresentative":"郝伟","capital":"N/A","businessScope":"办理存款、贷款、票据贴现、国内结算业务；办理个人储蓄业务；代理其他银行的金融业务；代理收付款项、及受托代办保险业务；买卖政府债券；代理发行、代理兑付、承销政府债券；提供保险箱业务。由县联社统一办理资金融通调剂业务；办理经中国银行业监督管理委员会批准的其他业务。","province":"新疆","city":"伊犁哈萨克","address":"新疆伊犁州昭苏县夏塔乡"},{"name":"莎车县阿拉买提乡供销社","code":"91653125230141415Y","registrationDay":"1989-04-18","character":"集体所有制","legalRepresentative":"凯尤木·萨伍提","capital":"60.9万人民币","businessScope":"农业生产资料、地膜，化肥（硝基复混肥除外）日用百货、文化用品、建筑材料、棉籽、农副产品","province":"新疆","city":"喀什","address":"莎车县新阿拉买提村"},{"name":"伽师县米夏乡供销社","code":"9165312972914130XT","registrationDay":"1989-04-19","character":"集体所有制","legalRepresentative":"库尔班·吐尔洪","capital":"71万人民币","businessScope":"化肥(硝基复混肥除外）、地膜、五金、日用百货、预包装食品、散装食品、粮油、副食品的销售；房屋租赁、商务咨询服务、电子商务、网络营销；农业种植；农副产品线上线下产品推广与销售。","province":"新疆","city":"喀什","address":"新疆喀什地区伽师县米夏乡"},{"name":"伽师县英买里乡供销社","code":"91653129718992045X","registrationDay":"1989-04-19","character":"集体所有制","legalRepresentative":"喀斯木·库宛","capital":"90万人民币","businessScope":"化肥(硝基复混肥除外）、地膜、五金、日用百货、预包装食品、散装食品、粮油、副食品的销售；房屋租赁、商务咨询服务、电子商务、网络营销；农业种植；农副产品线上线下产品推广与销售。","province":"新疆","city":"喀什","address":"新疆喀什地区伽师县英买里乡"},{"name":"巴楚县农村信用合作联社阿曼托格拉克信用社","code":"91653130679274373D","registrationDay":"1989-04-19","character":"N/A","legalRepresentative":"杨雯雯","capital":"N/A","businessScope":"办理存款、贷款、票据贴现、国内结算业务、办理个人储蓄业务，代理其他银行的金融业务、买卖政府债券、代理收付款项及受托代办保险业务.代理发行、代理兑付、承销政府债券，提供保险箱业务；由县联社统一办理资金融通调剂业务；办理经中国银行业监督管理委员会批准的其他业务 。","province":"新疆","city":"喀什","address":"新疆喀什地区巴楚县胜利东路(体委旁)"},{"name":"巴楚县英吾斯坦乡供销社","code":"916531302302403765","registrationDay":"1989-04-19","character":"集体所有制","legalRepresentative":"阿卜杜热合曼·吾舒尔","capital":"79.4万人民币","businessScope":"化肥、农用地膜、百货、纺织品、五金交电、服装、饲料、建材、厨房、卫生间用具零售，公用电话、房屋租赁服务。","province":"新疆","city":"喀什","address":"新疆喀什地区巴楚县英吾斯坦乡"},{"name":"英吉沙县棉麻公司城镇加工厂","code":"91653123930100198U","registrationDay":"1989-04-20","character":"集体分支机构(非法人)","legalRepresentative":"陈智斌","capital":"N/A","businessScope":"籽棉加工 籽棉收购；废旧物资回收。","province":"新疆","city":"喀什","address":"新疆喀什地区英吉沙县克孜勒路"},{"name":"英吉沙县棉麻公司芒申加工厂","code":"9165312393010018XU","registrationDay":"1989-04-20","character":"集体分支机构(非法人)","legalRepresentative":"陈智斌","capital":"N/A","businessScope":"籽棉加工；籽棉收购；废旧物资回收。","province":"新疆","city":"喀什","address":"新疆喀什地区英吉沙县芒申乡"},{"name":"察布查尔锡伯自治县琼博乐乡供销社","code":"91654022MA77587P4T","registrationDay":"1989-04-20","character":"集体所有制","legalRepresentative":"居来提?卡合尔曼","capital":"27.2万人民币","businessScope":"化肥，地膜，农副产品，畜产品，房屋租赁，饲料。","province":"新疆","city":"伊犁哈萨克","address":"新疆伊犁州察布查尔县琼博乐乡"},{"name":"英吉沙县棉麻公司克孜勒加工厂","code":"916531239301001714","registrationDay":"1989-04-20","character":"集体分支机构(非法人)","legalRepresentative":"陈智斌","capital":"N/A","businessScope":"籽棉加工；籽棉收购；废旧物资回收。","province":"新疆","city":"喀什","address":"新疆喀什地区英吉沙县克孜勒乡"},{"name":"察布查尔县农村信用合作联社海努克信用社","code":"91654022328855651F","registrationDay":"1989-04-20","character":"N/A","legalRepresentative":"木阿白特·阿布都卡德尔","capital":"N/A","businessScope":"经营中国银行业监督管理委员会依照有关法律、行政法规和其他规定批准的业务，经营范围以批准文件所列的为准。","province":"新疆","city":"伊犁哈萨克","address":"新疆伊犁察布查尔县海努克乡"},{"name":"尼勒克县益农供销社克令乡农资服务部","code":"91654028MA77TX4Q2M","registrationDay":"1989-04-20","character":"N/A","legalRepresentative":"开里曼·依布拉依木","capital":"N/A","businessScope":"种子、化肥、农药农膜销售。","province":"新疆","city":"伊犁哈萨克","address":"新疆伊犁州尼勒克县克令乡"},{"name":"英吉沙县棉麻公司乌恰加工厂","code":"91653123930100139Q","registrationDay":"1989-04-20","character":"集体分支机构(非法人)","legalRepresentative":"陈智斌","capital":"N/A","businessScope":"籽棉收购；废旧物资回收。","province":"新疆","city":"喀什","address":"新疆喀什地区英吉沙县乌恰乡"},{"name":"英吉沙县棉麻公司托甫洛克加工厂","code":"91653123930100745F","registrationDay":"1989-04-20","character":"集体分支机构(非法人)","legalRepresentative":"陈智斌","capital":"N/A","businessScope":"籽棉收购；废旧物资回收。","province":"新疆","city":"喀什","address":"新疆喀什地区英吉沙县托甫洛克乡"},{"name":"阿瓦提县乌鲁却勒镇供销合作社","code":"91652928229850433B","registrationDay":"1989-04-20","character":"集体所有制","legalRepresentative":"阿不都艾尼江·艾克然木","capital":"213万人民币","businessScope":"农作物（林木）种子、化肥、地膜销售，房屋租赁","province":"新疆","city":"阿克苏","address":"新疆阿克苏地区阿瓦提县乌鲁却勒镇"},{"name":"伽师县克孜勒苏乡供销社","code":"916531297981931897","registrationDay":"1989-04-20","character":"集体所有制","legalRepresentative":"图尔荪·图尔迪","capital":"63万人民币","businessScope":"化肥(硝基复混肥除外）、地膜、五金、日用百货、预包装食品、散装食品、粮油、副食品的销售；房屋租赁、商务咨询服务、电子商务、网络营销；农业种植；农副产品线上线下产品推广与销售。","province":"新疆","city":"喀什","address":"新疆喀什地区伽师县克孜勒苏乡"},{"name":"察布查尔县扎库齐牛录乡供销社","code":"91654022757685443Q","registrationDay":"1989-04-20","character":"集体所有制","legalRepresentative":"张传茂","capital":"20万人民币","businessScope":"化肥、农膜、土产、畜产品、农副产品销售。","province":"新疆","city":"伊犁哈萨克","address":"新疆伊犁州察布查尔县扎库齐牛录乡"},{"name":"尼勒克县益农供销社喀拉苏农资服务部","code":"91654028MA77TWTQ91","registrationDay":"1989-04-20","character":"集体分支机构(非法人)","legalRepresentative":"杨华宁","capital":"N/A","businessScope":"种子、化肥、农药，农膜、农具、各种农药药械，农畜产品收购","province":"新疆","city":"伊犁哈萨克","address":"新疆伊犁州尼勒克县喀拉苏乡"},{"name":"疏附县农村信用合作联社乌帕尔信用社","code":"91653121710825832Q","registrationDay":"1989-04-21","character":"N/A","legalRepresentative":"热合曼江·图尔贡","capital":"N/A","businessScope":"许可经营项目：办理存款、货款、票据贴现、国内结算业务、办理个人储蓄业务、代理收付款项及受托代办保险业务、买卖政府债劵、代理发行、代理兑付、承销政府债劵、提供保险箱服务、由县联社統一办理资金融通调剂业务、办理经中国银行监督管理委员会批准的其他业务","province":"新疆","city":"喀什","address":"新疆喀什地区疏附县乌帕尔乡"},{"name":"疏附县农村信用合作联社布拉克苏信用社","code":"91653121710825840K","registrationDay":"1989-04-21","character":"N/A","legalRepresentative":"阿布都热依穆·比拉力","capital":"N/A","businessScope":"办理存款、货款、票据贴现、国内结算业务、办理个人储蓄业务、代理收付款项及受托代办保险业务、买卖政府债劵、代理发行、代理兑付、承销政府债劵、提供保险箱服务、由县联社統一办理资金融通调剂业务、办理经中国银行监督管理委员会批准的其他业务","province":"新疆","city":"喀什","address":"新疆喀什地区疏附县布拉克苏乡"},{"name":"莎车县农业发展集团有限公司","code":"916531252301400177","registrationDay":"1989-04-21","character":"N/A","legalRepresentative":"张新奇","capital":"3,000(万元人民币)","businessScope":"各种农作物种子繁育、生产、加工、销售；牧草、瓜果种子繁育、收购、加工、生产、销售，农副产品收购、加工、储蓄、销售；花卉、苗木繁育、销售，农业技术推广服务；农业信息技术咨询服务；农业观光旅游；棉花收购、加工、销售；化肥(硝基复混肥除外)、地膜销售","province":"新疆","city":"喀什","address":"新疆喀什地区莎车县智慧路32号(农业大厦2楼)"},{"name":"疏附县农村信用合作联社吾库萨克信用社","code":"916531217108258163","registrationDay":"1989-04-21","character":"N/A","legalRepresentative":"马木提江·麦海提","capital":"N/A","businessScope":"办理存款、货款、票据贴现、国内结算业务、办理个人储蓄业务、代理收付款项及受托代办保险业务、买卖政府债劵、代理发行、代理兑付、承销政府债劵、提供保险箱服务、由县联社統一办理资金融通调剂业务、办理经中国银行监督管理委员会批准的其他业务","province":"新疆","city":"喀什","address":"新疆喀什地区疏附县吾库萨克乡"},{"name":"巴楚县阿瓦提镇供销社","code":"916531302302403840","registrationDay":"1989-04-21","character":"集体所有制","legalRepresentative":"阿卜杜热合曼·吾舒尔","capital":"71.4万人民币","businessScope":"化肥，塑料，百货，五金，家用电器，代办SIM卡，通讯设备，日用品，话把，房屋租赁。","province":"新疆","city":"喀什","address":"新疆喀什地区巴楚县阿瓦提镇"},{"name":"疏附县农村信用合作联社木什信用社","code":"916531217108259207","registrationDay":"1989-04-21","character":"N/A","legalRepresentative":"安外尔江·如则","capital":"N/A","businessScope":"办理存款、货款、票据贴现、国内结算业务、办理个人储蓄业务、代理收付款项及受托代办保险业务、买卖政府债劵、代理发行、代理兑付、承销政府债劵、提供保险箱服务、由县联社統一办理资金融通调剂业务、办理经中国银行监督管理委员会批准的其他业务","province":"新疆","city":"喀什","address":"新疆喀什地区疏附县木什乡"},{"name":"疏附县农村信用合作联社","code":"91653121710825795J","registrationDay":"1989-04-21","character":"N/A","legalRepresentative":"热合曼江·图尔贡","capital":"N/A","businessScope":"许可经营项目：办理存款、货款、票据贴现、国内结算业务、办理个人储蓄业务、代理收付款项及受托代办保险业务、买卖政府债劵、代理发行、代理兑付、承销政府债劵、提供保险箱服务、由县联社統一办理资金融通调剂业务、办理经中国银行监督管理委员会批准的其他业务","province":"新疆","city":"喀什","address":"新疆喀什地区疏附县人民南路18号"},{"name":"石河子新安农场第四加工厂","code":"916590013134316026","registrationDay":"1989-04-22","character":"国有企业","legalRepresentative":"张新革","capital":"N/A","businessScope":"棉花收购、棉花加工。网套加工。","province":"新疆","city":"石河子","address":"新疆石河子市142团"},{"name":"伊宁县农村信用合作联社潘津信用社","code":"9165400271085019XL","registrationDay":"1989-04-22","character":"N/A","legalRepresentative":"付翠玲","capital":"N/A","businessScope":"办理存款、贷款、票据帖现、国内结算业务；办理个人储蓄业务；代理其他银行的金融业务；代理收付款项及受托代办保险业务；买卖政府债券；代理发行、代理兑付、承销政府债券；提供保险箱服务；办理经中国银行业监督管理委员会批准的其他业务。","province":"新疆","city":"伊犁哈萨克","address":"新疆伊犁州伊宁市潘津乡"},{"name":"巴楚县阿拉根供销社","code":"91653130230240392T","registrationDay":"1989-04-22","character":"集体所有制","legalRepresentative":"艾力·伊纳耶提","capital":"110.8万人民币","businessScope":"食品、果品、饮料、糖果、调味品","province":"新疆","city":"喀什","address":"新疆喀什地区巴楚县阿拉格尔乡"},{"name":"民丰县农村信用合作联社萨勒吾则克信用社","code":"9165322777895389XP","registrationDay":"1989-04-22","character":"N/A","legalRepresentative":"穆太力普·伊卜拉伊木","capital":"0(万元人民币)","businessScope":"办理存款、贷款、票据贴现、国内结算业务；办理个人储蓄业务；代理其他银行的金融业务；代理收付款项及受托代办保险业务；买卖政府债卷；代理发行、代理兑付、承销政府债券；提供保险箱业务；由县联社统一办理资金融通调剂业务；办理由中国银行业监督管理委员会批准的其他业务。","province":"新疆","city":"和田","address":"新疆和田地区民丰县萨勒吾则克乡"},{"name":"新疆环宇建设工程(集团)有限责任公司","code":"91659006229491573D","registrationDay":"1989-04-22","character":"N/A","legalRepresentative":"王建民","capital":"51,141.0900(万)","businessScope":"对外承包工程；房屋建筑工程施工总承包壹级；水利水电工程施工总承包贰级；金属门窗工程专业承包叁级；起重设备安装专业承包叁级；机电设备安装工程专业承包叁级；送变电工程专业承包叁级；公路工程施工总承包贰级，市政公用工程施工总承包贰级，钢结构工程专业承包贰级，批发零售：其他机械设备及电子产品、其他化工产品、建材、五金交电、钢材、其他农畜产品，机械租赁，信息技术服务","province":"新疆","city":"巴音郭楞","address":"新疆铁门关市和谐路1号政府4楼"},{"name":"巴楚县色力布亚供销合作社","code":"91653130710834085B","registrationDay":"1989-04-23","character":"集体所有制","legalRepresentative":"艾力·伊纳耶提","capital":"170.2万人民币","businessScope":"食堂、烤包子、烤肉、打馕","province":"新疆","city":"喀什","address":"新疆喀什地区巴楚县色力布亚镇"},{"name":"莎车县荒地镇供销社","code":"916531252301414074","registrationDay":"1989-04-25","character":"集体所有制","legalRepresentative":"何新源","capital":"265.2万人民币","businessScope":"许可经营项目：","province":"新疆","city":"喀什","address":"新疆喀什地区莎车县荒地镇"},{"name":"莎车县吾达力克乡供销社第三门市部","code":"91653125798174332M","registrationDay":"1989-04-25","character":"集体分支机构(非法人)","legalRepresentative":"努尔艾合买提·托合提","capital":"N/A","businessScope":"化肥、农用薄膜、农副产品","province":"新疆","city":"喀什","address":"新疆喀什地区莎车县吾达力克乡"},{"name":"巴楚县群库恰克乡供销社","code":"916531302302404216","registrationDay":"1989-04-25","character":"集体所有制","legalRepresentative":"阿卜杜热合曼·吾舒尔","capital":"239.8万人民币","businessScope":"果品、食品、饮料、干果、蔬菜、正餐、肉、烟草制品零售，音像制品出租零售、理发服务（分支机构经营）;百货、五金、家用电器、厨房、卫生间用具及日用杂货、建材、化肥、农用地膜、畜产品零售，话吧、代收通讯设备话费、代办SIM卡、充值卡服务，农作物的种植","province":"新疆","city":"喀什","address":"新疆喀什地区巴楚县琼库恰克乡"},{"name":"莎车县荒地镇供销社第二十六门市部","code":"916531257981756344","registrationDay":"1989-04-25","character":"集体分支机构(非法人)","legalRepresentative":"麦麦提明·如孜","capital":"N/A","businessScope":"代销棉花、玉米、小麦、油料、瓜菜、甜菜、牧草、水稻包装种子、建材","province":"新疆","city":"喀什","address":"新疆喀什地区莎车县荒地镇"},{"name":"轮台县供销合作社联合社草湖基层社","code":"916528222295204509","registrationDay":"1989-04-25","character":"集体所有制","legalRepresentative":"吾守尔?阿木东","capital":"16万人民币","businessScope":"日用百货、日用杂品、日用化学品、服装鞋帽、针织、纺织品,五金交电零售。","province":"新疆","city":"巴音郭楞","address":"新疆巴州轮台县草湖乡"},{"name":"莎车县荒地镇供销社第三门市部","code":"916531257981756937","registrationDay":"1989-04-25","character":"集体分支机构(非法人)","legalRepresentative":"阿布都卡地尔·吐尔孙","capital":"N/A","businessScope":"化肥、农用薄膜、建材","province":"新疆","city":"喀什","address":"新疆喀什地区莎车县托木斯塘乡4村3组"},{"name":"莎车县荒地镇供销社第二十二门市部","code":"91653125798175642Y","registrationDay":"1989-04-25","character":"集体分支机构(非法人)","legalRepresentative":"如孜·托合提尼亚孜","capital":"N/A","businessScope":"化肥、农用薄膜、农机具、甘草、建材","province":"新疆","city":"喀什","address":"新疆喀什地区莎车县荒地镇"},{"name":"轮台县三农服务供销合作社哈尔巴克基层社","code":"91652822229520442E","registrationDay":"1989-04-25","character":"集体所有制","legalRepresentative":"阿不力孜·吾斯曼","capital":"16.8万人民币","businessScope":"日用百货、日用杂品、针纺织品、五金、服装鞋帽零售；房屋租赁、场地租赁*。","province":"新疆","city":"巴音郭楞","address":"新疆巴州轮台县哈尔巴克乡"},{"name":"伽师县玉代力克乡供销社","code":"91653129757683106C","registrationDay":"1989-04-25","character":"集体所有制","legalRepresentative":"阿布肚热合曼·佧迪尔","capital":"64.4万人民币","businessScope":"化肥(硝基复混肥除外）、地膜、五金、日用百货、预包装食品、散装食品、粮油、副食品的销售；农业种植；农副产品线上线下产品推广与销售。","province":"新疆","city":"喀什","address":"新疆喀什地区新疆伽师县玉代力克乡"},{"name":"莎车县吾达力克乡供销社","code":"916531252301414742","registrationDay":"1989-04-26","character":"集体所有制","legalRepresentative":"阿布力米提·阿布都拉","capital":"54.4万人民币","businessScope":"化肥、农用薄膜、其他日用品、五金、家用电器、农副产品（粮棉除外）、建材","province":"新疆","city":"喀什","address":"新疆喀什地区莎车县吾达力克乡"},{"name":"巩留县供销社东买里粮油加工厂","code":"91654024710854078L","registrationDay":"1989-04-26","character":"集体所有制","legalRepresentative":"马仁","capital":"18万人民币","businessScope":"许可经营项目：小麦、玉米、稻谷、油料加工、零售；粮食收购。一般经营项目：无。","province":"新疆","city":"伊犁哈萨克","address":"巩留县东买里乡"},{"name":"巴楚县夏马勒乡供销社","code":"9165313023024043XX","registrationDay":"1989-04-26","character":"集体所有制","legalRepresentative":"依明·肉孜","capital":"30.9万人民币","businessScope":"针织品、纺织品、化肥、农用地膜、畜产品批发、零售，育肥服务。","province":"新疆","city":"喀什","address":"巴楚县夏马勒乡"},{"name":"伊宁县农村信用合作联社墩麻扎信用社","code":"91654021710850237G","registrationDay":"1989-04-27","character":"N/A","legalRepresentative":"黄志刚","capital":"N/A","businessScope":"许可经营项目：经营中国银行业监督管理委员会依照有关法律、行政法规和其他规定批准的业务，经营范围以批准文件所列的为准。一般经营项目：房屋租赁。","province":"新疆","city":"伊犁哈萨克","address":"新疆伊犁州伊宁县墩麻扎镇"},{"name":"昭苏县农村信用合作联社喀拉苏信用社","code":"9165402693067014XD","registrationDay":"1989-04-27","character":"N/A","legalRepresentative":"马红军","capital":"N/A","businessScope":"许可经营项目：办理存款、贷款、票据贴现、国内结算业务；办理个人储蓄业务；代理其他银行的金融业务；代理收付款项、及受托代办保险业务；买卖政府债券；代理发行、代理兑付、承销政府债券；提供保险箱业务；由县联社统一办理资金融通调剂业务；办理经中国银行业监督管理委员会批准的其他业务。一般经营项目：无。","province":"新疆","city":"伊犁哈萨克","address":"新疆伊犁州昭苏县喀拉苏乡"},{"name":"巴楚县恰瓦克供销社","code":"91653130230240448X","registrationDay":"1989-04-27","character":"集体所有制","legalRepresentative":"修宏","capital":"72.2万人民币","businessScope":"百货、纺织品、厨房、卫生间用具及日用杂货、五金、家用电器、化肥、农用地膜、畜产品、建材、文具用品零售。","province":"新疆","city":"喀什","address":"新疆喀什地区巴楚县恰尔巴格乡"},{"name":"巴楚县阿纳库勒乡供销合作社","code":"916531307318127826","registrationDay":"1989-04-27","character":"集体所有制","legalRepresentative":"热夏提·艾比布拉","capital":"71.9万人民币","businessScope":"百货,纺织品,五金,化肥,地膜,畜产品。","province":"新疆","city":"喀什","address":"新疆喀什地区巴楚县阿纳库勒乡"},{"name":"新疆库尔勒市黄河白铁制品厂","code":"916528012294903432","registrationDay":"1989-04-28","character":"集体所有制","legalRepresentative":"库尔班·艾麦提","capital":"29.3万人民币","businessScope":"铁皮制品的加工修理，房屋出租。","province":"新疆","city":"巴音郭楞","address":"新疆巴州库尔勒市团结路"},{"name":"巴楚县阿克萨克玛热勒乡供销社","code":"91653130230240536C","registrationDay":"1989-04-28","character":"集体所有制","legalRepresentative":"依明·肉孜","capital":"139.9万人民币","businessScope":"五金家电、厨房、卫生间用具、纺织品、化肥、农用地膜、塑料制品、畜产品、服装鞋帽、文化用品、百货零售。","province":"新疆","city":"喀什","address":"新疆喀什地区巴楚县阿克萨克玛热勒乡"},{"name":"伊宁县曲鲁海供销合作社","code":"91654021230570287Q","registrationDay":"1989-04-28","character":"集体所有制","legalRepresentative":"陈爽","capital":"45.6万人民币","businessScope":"种子代销、化肥、农膜零售、农副产品、畜产品收购、房屋租赁、活畜交易、百货、土产日杂、五金交电零售、非生产废旧物质回收、市场开发(摊位租赁)、建材销售、其它商务服务。","province":"新疆","city":"伊犁哈萨克","address":"新疆伊犁州伊宁县曲鲁海乡"},{"name":"莎车县农村信用合作联社阿拉买提信用社","code":"91653125726954102H","registrationDay":"1989-04-29","character":"N/A","legalRepresentative":"亚森·尤努斯","capital":"N/A","businessScope":"许可经营项目：","province":"新疆","city":"喀什","address":"新疆喀什地区莎车县阿拉买提乡第12村6组"},{"name":"莎车县农村信用合作联社喀尔苏信用社","code":"9165312572695409XQ","registrationDay":"1989-04-29","character":"N/A","legalRepresentative":"努尔敦·吐尔孙","capital":"N/A","businessScope":"许可经营项目：","province":"新疆","city":"喀什","address":"新疆喀什地区莎车县喀尔苏乡第4村4组"},{"name":"莎车县农村信用合作联社米夏信用社","code":"91653125726953863B","registrationDay":"1989-04-29","character":"N/A","legalRepresentative":"依拉木·吐孙","capital":"N/A","businessScope":"许可经营项目：","province":"新疆","city":"喀什","address":"新疆喀什地区莎车县米夏乡第18村2组"},{"name":"莎车县农村信用合作联社恰热巴格信用社","code":"9165312572695388XX","registrationDay":"1989-04-29","character":"N/A","legalRepresentative":"帕提古力·吐拉普","capital":"N/A","businessScope":"许可经营项目：","province":"新疆","city":"喀什","address":"新疆喀什地区莎车县恰热巴格乡第7村3组"},{"name":"莎车县农村信用合作联社巴格阿瓦提信用社","code":"916531257269540736","registrationDay":"1989-04-29","character":"N/A","legalRepresentative":"牙森·吐尔孙","capital":"N/A","businessScope":"许可经营项目：","province":"新疆","city":"喀什","address":"新疆喀什地区莎车县巴格阿瓦提乡第11村1组"},{"name":"莎车县农村信用合作联社托木吾斯塘信用社","code":"91653125726953898X","registrationDay":"1989-04-29","character":"N/A","legalRepresentative":"艾尼玩·麦麦提","capital":"N/A","businessScope":"许可经营项目：许可经营项目","province":"新疆","city":"喀什","address":"新疆喀什地区莎车县托木吾斯塘乡乡巴扎内"},{"name":"莎车县农村信用合作联社英吾斯塘信用社","code":"91653125726953900H","registrationDay":"1989-04-29","character":"N/A","legalRepresentative":"阿布都热合曼·塔力莆","capital":"N/A","businessScope":"许可经营项目：","province":"新疆","city":"喀什","address":"新疆喀什地区莎车县英吾斯塘乡第4村3组"},{"name":"莎车县农村信用合作联社阿扎提巴格信用社","code":"91653125726953839T","registrationDay":"1989-04-29","character":"N/A","legalRepresentative":"图尔荪·卡伍孜","capital":"N/A","businessScope":"许可经营项目：","province":"新疆","city":"喀什","address":"新疆喀什地区莎车县阿扎提巴格乡第5村3组"},{"name":"莎车县农村信用合作联社依干其信用社","code":"916531257269540811","registrationDay":"1989-04-29","character":"N/A","legalRepresentative":"艾麦尔艾力·吐尔孙","capital":"N/A","businessScope":"许可经营项目：","province":"新疆","city":"喀什","address":"新疆喀什地区莎车县依干其镇第15村6组"},{"name":"莎车县农村信用合作联社艾力西湖信用社","code":"916531257269539947","registrationDay":"1989-04-29","character":"N/A","legalRepresentative":"吐尔孙托合提·喀迪尔","capital":"N/A","businessScope":"许可经营项目：","province":"新疆","city":"喀什","address":"新疆喀什地区莎车县艾力西湖镇第7村3组"},{"name":"莎车县农村信用合作联社荒地信用社","code":"91653125726954022X","registrationDay":"1989-04-29","character":"N/A","legalRepresentative":"玉苏甫卡迪尔·卡斯木","capital":"N/A","businessScope":"许可经营项目","province":"新疆","city":"喀什","address":"新疆喀什地区莎车县荒地镇第27村2组"},{"name":"莎车县农村信用合作联社帕克其信用社","code":"91653125726953978H","registrationDay":"1989-04-29","character":"N/A","legalRepresentative":"阿布力克木·阿布都克比尔","capital":"N/A","businessScope":"许可经营项目：","province":"新疆","city":"喀什","address":"新疆喀什地区莎车县帕克其乡第7村1组"},{"name":"莎车县农村信用合作联社依什库力信用社","code":"9165312572695396XH","registrationDay":"1989-04-29","character":"N/A","legalRepresentative":"吐尔孙尼牙孜·牙森","capital":"N/A","businessScope":"许可经营项目：","province":"新疆","city":"喀什","address":"新疆喀什地区莎车县依什库力乡第17村3组"},{"name":"莎车县农村信用合作联社墩巴格信用社","code":"91653125726954030Q","registrationDay":"1989-04-29","character":"N/A","legalRepresentative":"艾力开木·托合提","capital":"N/A","businessScope":"许可经营项目：","province":"新疆","city":"喀什","address":"新疆喀什地区莎车县墩巴格乡第6村2组"},{"name":"莎车县农村信用合作联社古勒巴格信用社","code":"91653125726953855G","registrationDay":"1989-04-29","character":"N/A","legalRepresentative":"古再努尔·斯迪克","capital":"N/A","businessScope":"许可经营项目：","province":"新疆","city":"喀什","address":"新疆喀什地区莎车县古勒巴格乡新城居委会五组"},{"name":"莎车县农村信用合作联社吾达力克信用社","code":"91653125726953919E","registrationDay":"1989-04-30","character":"N/A","legalRepresentative":"艾麦提尼牙孜·萨地克","capital":"N/A","businessScope":"许可经营项目：","province":"新疆","city":"喀什","address":"新疆喀什地区莎车县吾达力克乡第8村2组"},{"name":"莎车县农村信用合作联社阔什艾热克信用社","code":"916531257269540068","registrationDay":"1989-04-30","character":"N/A","legalRepresentative":"艾迪热斯·库尔班","capital":"N/A","businessScope":"许可经营项目：许可经营项目","province":"新疆","city":"喀什","address":"新疆喀什地区莎车县阔什艾热克乡第7村1组"},{"name":"博湖县乌兰再格森供销合作社","code":"91652829229660269H","registrationDay":"1989-04-30","character":"集体所有制","legalRepresentative":"李立功","capital":"19.6万人民币","businessScope":"零售：化肥；日用百货、针纺织品、五金交电、农机具、不再分装的包装种子；棉花收购，农副产品加工。","province":"新疆","city":"巴音郭楞","address":"新疆巴州博湖县乌兰再格森乡"},{"name":"阿瓦提县阿依巴格乡供销合作社","code":"91652928229850417M","registrationDay":"1989-04-30","character":"集体所有制","legalRepresentative":"依米尼江·阿不地卡地尔","capital":"129万人民币","businessScope":"化学肥料、地膜、五金交电产品、针纺织品、农业机械（不含拖拉机）销售，房屋租赁","province":"新疆","city":"阿克苏","address":"新疆阿克苏地区阿瓦提县阿依巴格乡"},{"name":"莎车县农村信用合作联社塔尕其信用社","code":"91653125726953986C","registrationDay":"1989-04-30","character":"N/A","legalRepresentative":"麦合木提·阿布都克热木","capital":"N/A","businessScope":"许可经营项目：许可经营项目","province":"新疆","city":"喀什","address":"新疆喀什地区莎车县塔尕其乡第14村6组"},{"name":"莎车县农村信用合作联社阿瓦提信用社","code":"91653125726954049M","registrationDay":"1989-04-30","character":"N/A","legalRepresentative":"麦麦提吐尔孙·吐热普","capital":"N/A","businessScope":"许可经营项目：","province":"新疆","city":"喀什","address":"新疆喀什地区莎车县阿瓦提镇第12村3组"},{"name":"莎车县农村信用合作联社阿斯兰巴格信用社","code":"916531257269539279","registrationDay":"1989-04-30","character":"N/A","legalRepresentative":"麦麦提尼亚孜·萨迪尔","capital":"N/A","businessScope":"许可经营项目：","province":"新疆","city":"喀什","address":"新疆喀什地区莎车县阿斯兰巴格乡第19村2组"},{"name":"莎车县农村信用合作联社卡群信用社","code":"916531257269540143","registrationDay":"1989-04-30","character":"N/A","legalRepresentative":"艾孜孜·牙森","capital":"N/A","businessScope":"许可经营项目：","province":"新疆","city":"喀什","address":"新疆喀什地区莎车县卡群乡第10村2组"},{"name":"阿瓦提县拜什艾日克镇供销合作社","code":"91652928929851592T","registrationDay":"1989-04-30","character":"集体所有制","legalRepresentative":"阿不拉·赛买提","capital":"156万人民币","businessScope":"化肥、地膜、农业机械、五金交电销售，房屋租赁","province":"新疆","city":"阿克苏","address":"新疆阿克苏地区阿瓦提县拜什艾日克镇"},{"name":"莎车县农村信用合作联社恰热克信用社","code":"916531257269539354","registrationDay":"1989-04-30","character":"N/A","legalRepresentative":"吾斯曼·艾麦尔","capital":"N/A","businessScope":"许可经营项目：","province":"新疆","city":"喀什","address":"新疆喀什地区莎车县恰热克镇第12村2组"},{"name":"哈巴河县农村信用合作联社","code":"91654324710874052Y","registrationDay":"1989-04-30","character":"N/A","legalRepresentative":"司云峰","capital":"6,211.7374(万)","businessScope":"中国银行业监督管理委员会依照有关法律、行政法规和其他规定批准的业务，经营范围以批准文件所列的为准；保险兼业代理业务，房屋租赁。","province":"新疆","city":"阿勒泰","address":"新疆阿勒泰地区哈巴河县阿克齐镇人民东路以北原人行楼"},{"name":"莎车县农村信用合作联社阿热勒信用社","code":"916531257269538716","registrationDay":"1989-04-30","character":"N/A","legalRepresentative":"努热曼古力·托合提","capital":"N/A","businessScope":"许可经营项目：","province":"新疆","city":"喀什","address":"新疆喀什地区莎车县阿热勒乡第2村6组"},{"name":"莎车县农村信用合作联社莎车镇信用社","code":"91653125726953847M","registrationDay":"1989-04-30","character":"N/A","legalRepresentative":"阿布都拉·阿巴拜克热","capital":"N/A","businessScope":"许可经营项目：许可经营项目","province":"新疆","city":"喀什","address":"新疆喀什地区莎车县莎车镇叶尔羌商场一楼"},{"name":"莎车县农村信用合作联社佰什坎特信用社","code":"91653125726954065B","registrationDay":"1989-04-30","character":"N/A","legalRepresentative":"阿布来提·赛麦提","capital":"N/A","businessScope":"许可经营项目：","province":"新疆","city":"喀什","address":"新疆喀什地区莎车县佰什坎特镇第9村1组"},{"name":"莎车县农村信用合作联社孜热甫夏提信用社","code":"91653125726953943Y","registrationDay":"1989-04-30","character":"N/A","legalRepresentative":"阿不都艾尼·巴克","capital":"N/A","businessScope":"许可经营项目：","province":"新疆","city":"喀什","address":"新疆喀什地区莎车县孜热甫夏提乡3村1组"},{"name":"沙雅县农村信用合作联社古勒巴格信用社","code":"91652924229770417Q","registrationDay":"1989-05-01","character":"N/A","legalRepresentative":"王衡","capital":"N/A","businessScope":"许可经营项目：金融业务。一般经营项目：无。","province":"新疆","city":"阿克苏","address":"新疆阿克苏地区沙雅县古勒巴格乡"},{"name":"沙雅县农村信用合作联社托依堡勒迪信用社","code":"91652924229770425K","registrationDay":"1989-05-01","character":"N/A","legalRepresentative":"徐元成","capital":"N/A","businessScope":"许可经营项目：金融业务。 一般经营项目：无。","province":"新疆","city":"阿克苏","address":"新疆阿克苏地区沙雅县托依堡勒迪镇"},{"name":"沙雅县农村信用合作联社塔南信用社","code":"91652924731815254R","registrationDay":"1989-05-01","character":"N/A","legalRepresentative":"徐元成","capital":"N/A","businessScope":"许可经营项目：金融业务。一般经营项目：无。","province":"新疆","city":"阿克苏","address":"新疆阿克苏地区沙雅县塔南乡"},{"name":"沙雅县农村信用合作联社英买力信用社","code":"9165292422977045X1","registrationDay":"1989-05-01","character":"N/A","legalRepresentative":"马玉强","capital":"N/A","businessScope":"许可经营项目：金融业务。一般经营项目：无。","province":"新疆","city":"阿克苏","address":"新疆阿克苏地区沙雅县英买力镇"},{"name":"沙雅县农村信用合作联社城镇信用社","code":"91652924229770409X","registrationDay":"1989-05-01","character":"N/A","legalRepresentative":"罗川","capital":"N/A","businessScope":"许可经营项目：金融业务。一般经营项目：无。","province":"新疆","city":"阿克苏","address":"新疆阿克苏地区沙雅县人民北路"},{"name":"沙雅县农村信用合作联社红旗信用社","code":"91652924229770476U","registrationDay":"1989-05-01","character":"N/A","legalRepresentative":"王海军","capital":"N/A","businessScope":"金融业务","province":"新疆","city":"阿克苏","address":"新疆阿克苏地区沙雅县红旗镇"},{"name":"沙雅县农村信用合作联社海楼信用社","code":"916529242297704419","registrationDay":"1989-05-01","character":"N/A","legalRepresentative":"喻浩","capital":"N/A","businessScope":"许可经营项目：金融业务。一般经营项目：无。","province":"新疆","city":"阿克苏","address":"新疆阿克苏地区沙雅县海楼乡"},{"name":"沙雅县农村信用合作联社塔里木信用社","code":"91652924MA7769TJ30","registrationDay":"1989-05-01","character":"N/A","legalRepresentative":"王海军","capital":"N/A","businessScope":"金融业务","province":"新疆","city":"阿克苏","address":"新疆阿克苏地区沙雅县塔里木乡"},{"name":"中国农业银行股份有限公司阿拉尔塔门支行","code":"916590027189408949","registrationDay":"1989-05-02","character":"股份有限公司 国有企业","legalRepresentative":"张斌","capital":"N/A","businessScope":"吸收公众存款，发放短期、中期、长期贷款...证券公司客户交易结算资金存管业务；证券投资基金托管业务；企业年金托管业务；产业投资基金托管业务；合格境外机构投资者境内证券投资托管业务；代理开放式基金业务；电话银行、网上银行、手机银行业务；金融衍生产品交易业务；经中国银行业监督管理机构等监管部门批准的其他业务。","province":"新疆","city":"阿拉尔","address":"新疆阿拉尔市塔门镇"},{"name":"伊宁县英塔木供销合作社","code":"91654021230570455T","registrationDay":"1989-05-03","character":"集体所有制","legalRepresentative":"胡财","capital":"19.7万人民币","businessScope":"化肥、农膜、百货、五金交电、土产品销售、种子代销、农副产品收购、牛羊养殖，非生产性废旧物资回收，房屋租赁，摊位租赁，建材销售,手工艺品制作，塑料制品加工，停车场，车辆交易，农机具销售，引进新技术、新品种、为农开展技能培训及技术咨询服务。","province":"新疆","city":"伊犁哈萨克","address":"新疆伊犁州伊宁县英塔木乡"},{"name":"洛浦县农村信用合作联社","code":"91653224710838676U","registrationDay":"1989-05-04","character":"N/A","legalRepresentative":"付胜","capital":"8,406.8367(万元人民币)","businessScope":"许可该机构经营中国银行业监督管理委员会依照有关法律、行政法规和其他规定批准的业务，经营范围以批准文件所列为准","province":"新疆","city":"和田","address":"新疆和田地区洛浦县和田路36号"},{"name":"乌什县供销合作联合社阿合雅镇基层供销社","code":"91652927MA777BWR9N","registrationDay":"1989-05-04","character":"集体所有制","legalRepresentative":"程刚","capital":"68.1万人民币","businessScope":"许可经营项目：无。一般经营项目：农副产品，纺织，服装及日用品，茶叶，建筑用五金，文具用品，农具，化肥、农膜批发零售，房屋租赁，土地租赁。","province":"新疆","city":"阿克苏","address":"新疆阿克苏地区乌什县阿合雅镇"},{"name":"和田县色格孜库勒乡供销社","code":"91653221230330232X","registrationDay":"1989-05-04","character":"集体所有制","legalRepresentative":"依明托合提·买吐送","capital":"13.9万人民币","businessScope":"农业生产资料、畜产品、干果收购。","province":"新疆","city":"和田","address":"新疆和田地区和田县色格孜库勒乡"},{"name":"和田县巴格其镇供销社","code":"91653221230330080H","registrationDay":"1989-05-04","character":"集体所有制","legalRepresentative":"托尔洪江·买吐尔送","capital":"54.5万人民币","businessScope":"化肥、农膜、日用百货、纺织品五金。","province":"新疆","city":"和田","address":"新疆和田地区和田县巴格其镇"},{"name":"新和县供销联社渭干供销社","code":"916529259297914030","registrationDay":"1989-05-08","character":"集体分支机构(非法人)","legalRepresentative":"古力尼沙木·司马义","capital":"N/A","businessScope":"农药（限制使用农药除外）、种子、化肥、农用地膜，小农具、滴灌带、百货、针织品销售；房屋租赁服务","province":"新疆","city":"阿克苏","address":"新疆阿克苏地区新和县渭干乡"},{"name":"新和县供销合作社联合社","code":"91652925229790303K","registrationDay":"1989-05-08","character":"集体所有制","legalRepresentative":"杨成秀","capital":"1313万人民币","businessScope":"农业生产资料、畜产品、五金交电、土产、百货、房屋租赁服务。","province":"新疆","city":"阿克苏","address":"新疆阿克苏地区新和县团结路"},{"name":"新和县供销联社尤鲁都斯巴格供销社","code":"91652925929791841L","registrationDay":"1989-05-08","character":"集体分支机构(非法人)","legalRepresentative":"古力尼沙木·司马义","capital":"N/A","businessScope":"许可经营项目：代销民乐、美丰农作物包装种子；农药。一般经营项目：化肥、农用地膜、小农具、滴灌带、百货、石灰销售，房屋租赁服务。","province":"新疆","city":"阿克苏","address":"新疆阿克苏地区新和县尤鲁都斯巴格乡"},{"name":"新和县供销联社生产资料公司","code":"91652925929791235X","registrationDay":"1989-05-09","character":"集体分支机构(非法人)","legalRepresentative":"魏勇","capital":"N/A","businessScope":"许可经营项目：农药。一般经营项目：农业生产资料","province":"新疆","city":"阿克苏","address":"新疆阿克苏地区新和县团结路"},{"name":"和田县布扎克乡供销社","code":"91653221230330355Y","registrationDay":"1989-05-09","character":"集体所有制","legalRepresentative":"麦提图尔荪·阿卜杜拉","capital":"35.2万人民币","businessScope":"农业生产资料、畜产品、干果收购。","province":"新疆","city":"和田","address":"新疆和田地区和田县布扎克乡"},{"name":"石河子市福利综合加工厂","code":"916590012310819600","registrationDay":"1989-05-13","character":"国有企业","legalRepresentative":"林建忠","capital":"275.4万人民币","businessScope":"生产用木制品、办公用品、塑料制品、骨灰盒制品、丧葬用品、五金制品、铝制门窗、工艺美术雕绘，礼仪服务。","province":"新疆","city":"石河子","address":"新疆石河子开发区东四路四十七号小区"},{"name":"巴楚县多来提巴格乡供销社","code":"91653130729144797R","registrationDay":"1989-05-13","character":"集体所有制","legalRepresentative":"热夏提·艾比布拉","capital":"87.9万人民币","businessScope":"化肥、农用地膜零售。","province":"新疆","city":"喀什","address":"新疆喀什地区巴楚县多来提巴格乡"},{"name":"轮台县三农服务供销合作社策达雅基层社","code":"91652822229520426Q","registrationDay":"1989-05-16","character":"集体所有制","legalRepresentative":"阿不力孜·吾斯曼","capital":"42.6万人民币","businessScope":"日用百货、日用杂品、针纺织品、服装鞋帽、五金交电零售；房屋租赁*。","province":"新疆","city":"巴音郭楞","address":"新疆巴州轮台县策达雅乡"},{"name":"轮台县农村信用合作联社","code":"91652822229520610G","registrationDay":"1989-05-16","character":"N/A","legalRepresentative":"东长军","capital":"16,222.0173(万)","businessScope":"许可该机构经营中国银行业监督管理委员会依照有关法律、行政法规和其他规定批准的业务，经营范围以批准文件所列的为准；房屋租赁。***。","province":"新疆","city":"巴音郭楞","address":"新疆巴州轮台县文化路与新新路交汇处"},{"name":"轮台县三农服务供销合作社大道南基层社","code":"916528222295204696","registrationDay":"1989-05-16","character":"集体所有制","legalRepresentative":"阿不力孜·吾斯曼","capital":"26.8万人民币","businessScope":"牲畜饲养；棉花种植；日用百货、日用杂品、日用化学品、服装鞋帽、针纺织品、五金交电、家用电器零售；房屋租赁、场地租赁*。(管控要素除外)","province":"新疆","city":"巴音郭楞","address":"新疆巴州轮台县迪那路"},{"name":"英吉沙县农村信用合作联社萨罕信用社","code":"91653123230100920R","registrationDay":"1989-05-17","character":"N/A","legalRepresentative":"阿布拉江·阿布都热合曼","capital":"N/A","businessScope":"许可经营项目：（一）办理存款、贷款、票据贴现，国内结算业务；（二）办理个人储蓄业务；（三）其他银行的金融业务；（四）代理收付款项及委托代办保险业务；（五）买卖政府债券；（六）代理发行、代理兑付、承销政府债券业务；（七）提供保险箱业务；（八）由县联社统一办理资金融通调剂业务；","province":"新疆","city":"喀什","address":"新疆喀什地区英吉沙县萨罕乡"},{"name":"英吉沙县农村信用合作联社色提力信用社","code":"91653123230101034B","registrationDay":"1989-05-17","character":"N/A","legalRepresentative":"努尔艾力·努尔麦麦提","capital":"N/A","businessScope":"（一）办理存款、贷款、票据贴现，国内结算业务；（二）办理个人储蓄业务；（三）其他银行的金融业务；（四）代理收付款项及委托代办保险业务；（五）买卖政府债券；（六）代理发行、代理兑付、承销政府债券业务；（七）提供保险箱业务；（八）由县联社统一办理资金融通调剂业务；","province":"新疆","city":"喀什","address":"新疆喀什地区英吉沙县色提力乡"},{"name":"英吉沙县农村信用合作联社艾古斯信用社","code":"9165312323010100XM","registrationDay":"1989-05-17","character":"N/A","legalRepresentative":"麦合木提·穆赛力木","capital":"N/A","businessScope":"（一）办理存款、贷款、票据贴现，国内结算业务；（二）办理个人储蓄业务；（三）其他银行的金融业务；（四）代理收付款项及委托代办保险业务；（五）买卖政府债券；（六）代理发行、代理兑付、承销政府债券业务；（七）提供保险箱业务；（八）由县联社统一办理资金融通调剂业务；","province":"新疆","city":"喀什","address":"新疆喀什地区英吉沙县艾古斯乡"},{"name":"英吉沙县农村信用合作联社龙甫信用社","code":"91653123230101018M","registrationDay":"1989-05-17","character":"N/A","legalRepresentative":"麦合木提·穆赛力木","capital":"N/A","businessScope":"（一）办理存款、贷款、票据贴现，国内结算业务；（二）办理个人储蓄业务；（三）其他银行的金融业务；（四）代理收付款项及委托代办保险业务；（五）买卖政府债券；（六）代理发行、代理兑付、承销政府债券业务；（七）提供保险箱业务；（八）由县联社统一办理资金融通调剂业务；","province":"新疆","city":"喀什","address":"新疆喀什地区英吉沙县龙甫乡"},{"name":"英吉沙县农村信用合作联社克孜勒信用社","code":"9165312323010098XR","registrationDay":"1989-05-17","character":"N/A","legalRepresentative":"麦麦提·萨伍提","capital":"N/A","businessScope":"（一）办理存款、贷款、票据贴现，国内结算业务；（二）办理个人储蓄业务；（三）其他银行的金融业务；（四）代理收付款项及委托代办保险业务；（五）买卖政府债券；（六）代理发行、代理兑付、承销政府债券业务；（七）提供保险箱业务；（八）由县联社统一办理资金融通调剂业务；","province":"新疆","city":"喀什","address":"新疆喀什地区英吉沙县克孜勒乡"},{"name":"英吉沙县农村信用合作联社乌恰信用社","code":"91653123230100998R","registrationDay":"1989-05-17","character":"N/A","legalRepresentative":"阿布都伟力·阿布都拉","capital":"N/A","businessScope":"（一）办理存款、贷款、票据贴现，国内结算业务；（二）办理个人储蓄业务；（三）其他银行的金融业务；（四）代理收付款项及委托代办保险业务；（五）买卖政府债券；（六）代理发行、代理兑付、承销政府债券业务；（七）提供保险箱业务；","province":"新疆","city":"喀什","address":"新疆喀什地区英吉沙县乌恰乡"},{"name":"英吉沙县农村信用合作联社苏盖提信用社","code":"916531232301009637","registrationDay":"1989-05-17","character":"N/A","legalRepresentative":"赛麦提·伊德日斯","capital":"N/A","businessScope":"（一）办理存款、贷款、票据贴现，国内结算业务；（二）办理个人储蓄业务；（三）其他银行的金融业务；（四）代理收付款项及委托代办保险业务；（五）买卖政府债券；（六）代理发行、代理兑付、承销政府债券业务；（七）提供保险箱业务；（八）由县联社统一办理资金融通调剂业务；","province":"新疆","city":"喀什","address":"新疆喀什地区英吉沙县苏盖提乡"},{"name":"英吉沙县农村信用合作联社城关信用社","code":"91653123230100912Y","registrationDay":"1989-05-17","character":"N/A","legalRepresentative":"帕提古丽·麦麦提","capital":"N/A","businessScope":"（一）办理存款、贷款、票据贴现，国内结算业务；（二）办理个人储蓄业务；（三）其他银行的金融业务；（四）代理收付款项及委托代办保险业务；（五）买卖政府债券；（六）代理发行、代理兑付、承销政府债券业务；（七）提供保险箱业务；（八）由县联社统一办理资金融通调剂业务；","province":"新疆","city":"喀什","address":"新疆喀什地区英吉沙县艾古斯路"},{"name":"英吉沙县农村信用合作联社芒辛信用社","code":"91653123230101026G","registrationDay":"1989-05-17","character":"N/A","legalRepresentative":"托合提·努尔艾买提","capital":"N/A","businessScope":"（一）办理存款、贷款、票据贴现，国内结算业务；（二）办理个人储蓄业务；（三）其他银行的金融业务；（四）代理收付款项及委托代办保险业务；（五）买卖政府债券；（六）代理发行、代理兑付、承销政府债券业务；（七）提供保险箱业务；（八）由县联社统一办理资金融通调剂业务；","province":"新疆","city":"喀什","address":"新疆喀什地区英吉沙县芒辛乡"},{"name":"英吉沙县农村信用合作联社乔勒潘信用社","code":"91653123230100939N","registrationDay":"1989-05-17","character":"N/A","legalRepresentative":"阿卜杜瓦哈普·伊米尔","capital":"N/A","businessScope":"（一）办理存款、贷款、票据贴现，国内结算业务；（二）办理个人储蓄业务；（三）其他银行的金融业务；（四）代理收付款项及委托代办保险业务；（五）买卖政府债券；（六）代理发行、代理兑付、承销政府债券业务；（七）提供保险箱业务；（八）由县联社统一办理资金融通调剂业务；","province":"新疆","city":"喀什","address":"新疆喀什地区英吉沙县乔尔旁乡"},{"name":"新疆巴音工程建设(集团)有限公司","code":"91652800710887929A","registrationDay":"1989-05-18","character":"N/A","legalRepresentative":"马云","capital":"5,139.5521(万)","businessScope":"房屋建筑工程施工、市政公用工程施工、建筑装修装饰工程，园林工程，工程的挖土运土；起重设备安装工程；钢结构工程；防腐保温工程，房屋租赁，广告牌安装，园林绿化工程，混凝土预制构件工程，管道工程建筑。","province":"新疆","city":"巴音郭楞","address":"新疆巴州库尔勒市萨依巴格辖区人民东路北侧3号12层"},{"name":"温宿县阿热勒基层供销社","code":"91652922229730730A","registrationDay":"1989-05-22","character":"集体所有制","legalRepresentative":"张自力","capital":"14万人民币","businessScope":"农药","province":"新疆","city":"阿克苏","address":"新疆阿克苏地区温宿县阿热勒镇"},{"name":"温宿县托乎拉乡基层供销社","code":"91652922229730853B","registrationDay":"1989-05-22","character":"集体所有制","legalRepresentative":"张自力","capital":"29万人民币","businessScope":"无 农药","province":"新疆","city":"阿克苏","address":"新疆阿克苏地区温宿县托乎拉乡"},{"name":"温宿县吐木秀克镇基层供销社","code":"916529222297307572","registrationDay":"1989-05-22","character":"集体所有制","legalRepresentative":"张自力","capital":"26万人民币","businessScope":"农药","province":"新疆","city":"阿克苏","address":"新疆阿克苏地区温宿县吐木秀克镇"},{"name":"温宿县恰合拉克乡基层供销社","code":"91652922229730781J","registrationDay":"1989-05-22","character":"集体所有制","legalRepresentative":"张自力","capital":"71万人民币","businessScope":"无 农药","province":"新疆","city":"阿克苏","address":"新疆阿克苏地区温宿县恰合拉克乡"},{"name":"温宿县佳木镇基层供销社","code":"916529222297308023","registrationDay":"1989-05-22","character":"集体所有制","legalRepresentative":"张自力","capital":"20万人民币","businessScope":"农药","province":"新疆","city":"阿克苏","address":"新疆阿克苏地区温宿县佳木镇"},{"name":"温宿县农村信用合作联社","code":"91652922229731397N","registrationDay":"1989-05-22","character":"N/A","legalRepresentative":"牟光辉","capital":"26,924.7100(万)","businessScope":"办理存款、贷款、票据贴现、国内结算业务；办理个人储蓄业务；代理其他银行的金融业务；办理收付款项，保险兼业代理业务；买卖政府债券；代理发行、代理兑换、承销政府债劵；提供保险箱业务；由县联社统一办理资金融通调剂业务；办理中国银行业监督管理委员会批准的其他业务；供热服务；房屋租赁服务","province":"新疆","city":"阿克苏","address":"新疆阿克苏地区温宿县阿温大道118号"},{"name":"和田县拉依喀乡供销社","code":"91653221230330320C","registrationDay":"1989-05-23","character":"集体所有制","legalRepresentative":"如则托合提·伊德日斯","capital":"71.5万人民币","businessScope":"化肥、地膜、日用百货、小五金、纺织品销售；畜产品、干鲜果收购销售；房屋租赁。","province":"新疆","city":"和田","address":"新疆和田地区和田县拉依喀乡"},{"name":"新疆塔城储绿粮油购销集团有限公司","code":"916542012307509154","registrationDay":"1989-05-24","character":"N/A","legalRepresentative":"常纪东","capital":"10,621.7600(万)","businessScope":"收购：小麦、玉米、葵花籽、红花籽、油菜籽、打瓜籽、稻谷；农副食品及植物油加工及销售；销售：机械设备及配件；建筑五金材料；谷物种植；财产租赁；车辆运输、货物装卸搬运及货物信息服务,仓储服务,化肥、各类农作物种子、农膜。","province":"新疆","city":"塔城","address":"新疆塔城地区塔城市生产街3号"},{"name":"阿瓦提县供销合作联社","code":"916529282298503965","registrationDay":"1989-05-29","character":"集体所有制","legalRepresentative":"黄敏","capital":"2331万人民币","businessScope":"种子、棉麻、化肥、地膜、农具、五金交电、建筑材料、化工、棉纺针织品、家电零售；农副产品收购、加工、经营、干鲜果品收购销售，房屋租赁","province":"新疆","city":"阿克苏","address":"新疆阿克苏地区阿瓦提县建设北路27号"},{"name":"阿瓦提县农村信用合作联社","code":"9165292822985045XX","registrationDay":"1989-05-29","character":"N/A","legalRepresentative":"范志明","capital":"5,100(万)","businessScope":"办理存款、贷款、票据贴现、国内结算业务；办理个人储蓄业务；代理其他银行的金融业务；代理收付款项及受托代办保险业务；买卖政府债券；代理发行、代理兑付、承销政府债券；提供保险箱服务；由县联社统一办理资金融通调剂业务；办理经中国银行业监督管理委员会批准的其他业务","province":"新疆","city":"阿克苏","address":"新疆阿克苏地区阿瓦提县光明中路23-3号"},{"name":"第八师一四九团联合加工厂","code":"916590019997801520","registrationDay":"1989-05-29","character":"国有企业","legalRepresentative":"韩宏江","capital":"N/A","businessScope":"轧花。","province":"新疆","city":"石河子","address":"新疆石河子市东阜城镇一四九团团部"},{"name":"新疆昊星八十二棉业有限公司","code":"91652722229430260Y","registrationDay":"1989-05-30","character":"有限责任公司","legalRepresentative":"高岩","capital":"500万人民币","businessScope":"籽棉收购、加工。皮棉购销、棉短绒加工、销售。","province":"新疆","city":"阿勒泰","address":"新疆双河市八十二团建设路二号"},{"name":"疏附县西域供销有限责任公司","code":"916531212300605518","registrationDay":"1989-06-01","character":"有限责任公司","legalRepresentative":"杨其亮","capital":"200万人民币","businessScope":"农作物种子委托代销。通过边境小额贸易方式向毗邻国家开展各类商品及技术的进出口业务、国家限制进出口的商品及技术除外。允许经营边贸项下废钢、废铜、废铝废塑料等国家核定公司经营的五种废旧物资的进口、","province":"新疆","city":"喀什","address":"新疆喀什地区疏附县人民南路2号"},{"name":"焉耆回族自治县七个星供销社","code":"9165282622960120XN","registrationDay":"1989-06-03","character":"集体所有制","legalRepresentative":"刘桂新","capital":"13万人民币","businessScope":"农药零售；批发零售：化肥、农用地膜。","province":"新疆","city":"巴音郭楞","address":"新疆巴州焉耆县七个星镇"},{"name":"和硕县乌什塔拉供销社","code":"91652828229640129R","registrationDay":"1989-06-03","character":"集体所有制","legalRepresentative":"孔海祥","capital":"109.6万人民币","businessScope":"零售：化肥（硝基复混肥除外），日用百货，土产品，五金交电","province":"新疆","city":"巴音郭楞","address":"新疆巴州和硕县乌什塔拉乡"},{"name":"和静县八棵树供销社斜米乃尔分销店","code":"91652827929622714B","registrationDay":"1989-06-04","character":"集体分支机构(非法人)","legalRepresentative":"陈治健","capital":"N/A","businessScope":"零售：化肥、微肥、叶面肥、滴灌肥、农用薄膜、日用杂品、瓶装液化气、滴灌带、塑料制品、农药（剧毒农药除外）","province":"新疆","city":"巴音郭楞","address":"新疆巴州和静县协比乃尔布呼乡"},{"name":"精河县农村信用合作联社托托信用社","code":"91652722625281180Q","registrationDay":"1989-06-04","character":"N/A","legalRepresentative":"杨国锋","capital":"N/A","businessScope":"经营中国银行业监督管理委员会依照有关法律、行政法规和其他规定批准的业务，经营范围以批准文件所列的为准 无。","province":"新疆","city":"博尔塔拉","address":"新疆博州精河县托托乡"},{"name":"呼图壁县新兴马鞍制造厂","code":"91652323X25227527T","registrationDay":"1989-06-06","character":"个人独资企业","legalRepresentative":"王玉成","capital":"N/A","businessScope":"马鞍、木器制造、销售。","province":"新疆","city":"昌吉","address":"新疆昌吉州呼图壁县五工台乡"},{"name":"哈密城郊供销合作社","code":"91652200229122874P","registrationDay":"1989-06-06","character":"集体所有制","legalRepresentative":"王国庆","capital":"34.4万人民币","businessScope":"农药；日用百货、五金（不含射钉枪弹）、交电、化工产品(不含化学危险品)、化肥、农膜、农机配件、锅炉配件、包装棉种的销售；预包装食品兼散装食品（不含婴幼儿配方乳粉、乳粉、液体乳、其他乳制品）零售","province":"新疆","city":"哈密","address":"新疆哈密市伊州区陶家宫镇（老乡政府对面）"},{"name":"石河子一三四团加工厂","code":"91659001999793025X","registrationDay":"1989-06-06","character":"N/A","legalRepresentative":"张希军","capital":"N/A","businessScope":"皮棉加工。","province":"新疆","city":"石河子","address":"新疆石河子市一三四团团部"},{"name":"和静县巴润哈尔莫墩供销社综合服务部","code":"91652827770360766B","registrationDay":"1989-06-07","character":"集体分支机构(非法人)","legalRepresentative":"花雷","capital":"N/A","businessScope":"零售：化肥、农膜、种子、农药（剧毒农药除外）","province":"新疆","city":"巴音郭楞","address":"新疆巴州和静县巴润哈尔莫墩镇"},{"name":"巴楚县供销合作社联合社","code":"916531307269678435","registrationDay":"1989-06-07","character":"集体所有制","legalRepresentative":"段喜缤","capital":"196.5万人民币","businessScope":"预包装食品兼散装食品批发兼零售","province":"新疆","city":"喀什","address":"新疆喀什地区巴楚县文化西路"},{"name":"和静县八棵树供销社生产资料门市部","code":"91652827929622669A","registrationDay":"1989-06-07","character":"集体分支机构(非法人)","legalRepresentative":"张作宗","capital":"N/A","businessScope":"零售：化肥、微肥、滴灌肥、叶面肥、农业机械、农用薄膜、塑料制品、滴灌带","province":"新疆","city":"巴音郭楞","address":"新疆巴州和静县乃门莫墩乡"},{"name":"石河子市瞭远联合加工厂","code":"91659001231080853B","registrationDay":"1989-06-07","character":"集体所有制","legalRepresentative":"张海东","capital":"173.2万人民币","businessScope":"皮棉，棉花及副产品的销售。","province":"新疆","city":"石河子","address":"新疆石河子市石河子乡西郊集"},{"name":"温泉县安格里格供销社","code":"9165272322945166XL","registrationDay":"1989-06-08","character":"集体所有制","legalRepresentative":"曹湘江","capital":"66万人民币","businessScope":"许可经营项目：（具体经营项目及期限以有关部门的批准文件或颁发的许可证、资质证书为准）：不再分装的国标包装种子、有毒品（农药）剧毒品除外","province":"新疆","city":"博尔塔拉","address":"温泉县安格里格乡"},{"name":"新疆四运集团公司第六车队","code":"91652800712989590C","registrationDay":"1989-06-08","character":"N/A","legalRepresentative":"艾萨江·买斯木","capital":"N/A","businessScope":"危险货物运输（2类1项）、危险货物运输（2类2项）、危险货物运输（2类3项）、危险货物运输（8类)","province":"新疆","city":"巴音郭楞","address":"新疆巴州库尔勒市龙山小区"},{"name":"新疆四运集团公司第一车队","code":"91652800729187121U","registrationDay":"1989-06-08","character":"N/A","legalRepresentative":"刘联卫","capital":"N/A","businessScope":"普通货物运输；大型物件运输（类别：一级)；批发零售：工程机械及配件","province":"新疆","city":"巴音郭楞","address":"新疆巴州库尔勒市314国道养路征稽所旁"},{"name":"新疆四运集团公司第三车队","code":"916528009294910804","registrationDay":"1989-06-08","character":"N/A","legalRepresentative":"郭世民","capital":"N/A","businessScope":"危险货物运输（2类1项）危险货物运输（2雷2项）危险货物运输（2类3项）危险货物运输（3类）危险货物运输（8类)","province":"新疆","city":"巴音郭楞","address":"新疆巴州库尔勒市塔什店路"},{"name":"库尔勒市塔什店陶粒制品厂","code":"91652801229494360P","registrationDay":"1989-06-08","character":"国有企业","legalRepresentative":"彭德军","capital":"357万人民币","businessScope":"制造及批发零售：陶粒及制品。","province":"新疆","city":"巴音郭楞","address":"新疆巴州库尔勒市塔什店"},{"name":"新疆四运集团公司","code":"916528007108061059","registrationDay":"1989-06-08","character":"N/A","legalRepresentative":"廖军攻","capital":"3,444(万)","businessScope":"县内班车客运、县际班车客运、市际班车客运、省际班车客运、市际班车客运（小轿车）、县际班车客运（小轿车）、县际包车客运、市际包车客运、省际包车客运、市际非定线旅游客运、道路普通货物运输、大型物件运输（类别：一级）、危险货物运输（类别：一类、二类一项、二类二项、二类三项、三类、八类）；成品油零售（限分支机构经营）；批发零售：其他机械设备及电子产品、汽车及摩托车配件、建材、针纺织品、其他化工产品、其他日用品、有色金属材料、其他农畜产品、润滑油、服装、鞋帽、日用杂货、五金交电（切割机、打磨机、电焊机、电钻机、发电机、粉碎机、机床除外）、饲料、文具用品、钢材，货运信息，洗车，仓储服务，家具销售","province":"新疆","city":"巴音郭楞","address":"新疆巴州库尔勒市交通东路27号"},{"name":"新疆四运集团公司第二车队","code":"916528009294910729","registrationDay":"1989-06-08","character":"N/A","legalRepresentative":"陈崇达","capital":"N/A","businessScope":"普通货物运输；大型物件运输","province":"新疆","city":"巴音郭楞","address":"新疆巴州库尔勒市天山西路"},{"name":"新疆四运集团公司客运队","code":"91652800929491101L","registrationDay":"1989-06-08","character":"N/A","legalRepresentative":"李少昆","capital":"N/A","businessScope":"县内班车客运；县际班车客运；县际小轿车班车客运；地际班车客运；地际小轿车班车客运；地际包车客运；省际班车客运；省际包车客运。","province":"新疆","city":"巴音郭楞","address":"新疆巴州库尔勒市铁门关路"},{"name":"新疆四运集团公司第四车队","code":"91652800712989566U","registrationDay":"1989-06-08","character":"N/A","legalRepresentative":"艾萨江·买斯木","capital":"N/A","businessScope":"危险货物运输（2类1项）、危险货物运输（2类2项）、危险货物运输（2类3项）、危险货物运输（3类）、危险货物运输（8类)","province":"新疆","city":"巴音郭楞","address":"新疆巴州库尔勒市龙山小区"},{"name":"新疆四运集团公司第七车队","code":"91652800929491128C","registrationDay":"1989-06-08","character":"N/A","legalRepresentative":"徐新良","capital":"N/A","businessScope":"大型物件运输","province":"新疆","city":"巴音郭楞","address":"新疆巴州库尔勒市新城区314国道东部"},{"name":"第八师一五〇团加工三厂","code":"91659001999780187J","registrationDay":"1989-06-09","character":"国有企业","legalRepresentative":"耿江平","capital":"N/A","businessScope":"皮棉加工，棉短绒加工。","province":"新疆","city":"石河子","address":"新疆石河子一五零团良一连"},{"name":"塔城市恰夏基层供销社","code":"91654201230751280B","registrationDay":"1989-06-10","character":"集体所有制","legalRepresentative":"杨战虎","capital":"40万人民币","businessScope":"销售：纺织品、百货、五金交电、化工、化肥、棉麻土产品。","province":"新疆","city":"塔城","address":"新疆塔城地区塔城市恰夏乡"},{"name":"塔城市阿西尔基层供销社","code":"91654201230751862H","registrationDay":"1989-06-12","character":"集体所有制","legalRepresentative":"杨战虎","capital":"43.1万人民币","businessScope":"销售：纺织品、百货、五金交电、化工产品","province":"新疆","city":"塔城","address":"新疆塔城地区塔城市阿西尔乡"},{"name":"塔城市喀拉哈巴克基层供销社","code":"91654201230751336E","registrationDay":"1989-06-12","character":"集体所有制","legalRepresentative":"杨战虎","capital":"43万人民币","businessScope":"销售：百货、纺织品、五金交电、化肥、农膜、棉麻土产品、日用品、农产品","province":"新疆","city":"塔城","address":"新疆塔城地区塔城市喀拉哈巴克乡"},{"name":"塔城市博孜达克基层供销社","code":"91654201230751440J","registrationDay":"1989-06-12","character":"集体所有制","legalRepresentative":"杨战虎","capital":"33.4万人民币","businessScope":"销售：纺织品、百货、五金交电、化工；棉麻土产品、化肥、日用杂品、农用地膜、废旧塑料杂品收购、畜产品收购","province":"新疆","city":"塔城","address":"新疆塔城地区塔城市博孜达克农场"},{"name":"博乐市青得里乡供销合作社","code":"916527012294015072","registrationDay":"1989-06-14","character":"集体所有制","legalRepresentative":"阿不都热西提","capital":"41.7万人民币","businessScope":"有毒品（杀虫剂、除草剂、杀菌剂、植物生长调节剂）批发、零售","province":"新疆","city":"博尔塔拉","address":"新疆博州博乐市青得里乡"},{"name":"莎车县阿瓦提供销社","code":"91653125230141327G","registrationDay":"1989-06-15","character":"集体所有制","legalRepresentative":"阿卜力米提·阿伍提","capital":"118万人民币","businessScope":"许可经营项目：无。一般经营项目：一般经营项目","province":"新疆","city":"喀什","address":"莎车县阿瓦提镇"},{"name":"和静县巴音布鲁克供销社水电大队综合门市部","code":"91652827686451964E","registrationDay":"1989-06-16","character":"集体分支机构(非法人)","legalRepresentative":"严宏翔","capital":"N/A","businessScope":"零售：农药","province":"新疆","city":"巴音郭楞","address":"新疆巴州和静县哈尔莫敦镇文化路富民安居小区1号楼2号门面"},{"name":"和静县巴音布鲁克供销社","code":"916528272296213151","registrationDay":"1989-06-17","character":"集体所有制","legalRepresentative":"廖伟文","capital":"120万人民币","businessScope":"零售：农药、烟","province":"新疆","city":"巴音郭楞","address":"新疆巴州和静县巴音布鲁克区"},{"name":"吉木乃县农村信用合作联社喀尔交信用社","code":"916543269310412576","registrationDay":"1989-06-20","character":"N/A","legalRepresentative":"代松春","capital":"N/A","businessScope":"以金融许可证为准。","province":"新疆","city":"阿勒泰","address":"新疆阿勒泰地区吉木乃县喀尔交镇"},{"name":"温泉县查干屯格供销社","code":"91652723229451723M","registrationDay":"1989-06-20","character":"集体所有制","legalRepresentative":"郭业成","capital":"70万人民币","businessScope":"许可经营项目：（具体经营项目及期限以有关部门的批准文件或颁发的许可证、资质证书为准）:销售不再分装的国标包装种子、有毒品","province":"新疆","city":"博尔塔拉","address":"温泉县查干屯格乡"},{"name":"乌什县农村信用合作联社燕山信用社","code":"91652927229830221T","registrationDay":"1989-06-20","character":"N/A","legalRepresentative":"阿布都黑力力·阿布都热依木","capital":"N/A","businessScope":"许可经营项目：","province":"新疆","city":"阿克苏","address":"新疆阿克苏地区乌什县热斯太街20号"},{"name":"石河子新安农场第三加工厂","code":"916590013134304666","registrationDay":"1989-06-22","character":"国有企业","legalRepresentative":"李新利","capital":"N/A","businessScope":"棉花加工。棉花收购。","province":"新疆","city":"石河子","address":"新疆石河子市142团"},{"name":"察布查尔县农村信用合作联社扎库齐牛录信用社","code":"916540223288558544","registrationDay":"1989-06-23","character":"N/A","legalRepresentative":"张伟","capital":"N/A","businessScope":"经营中国银行业监督管理委员会依照有关法律、行政法规和其他规定批准的业务，经营范围以批准文件所列的为准。","province":"新疆","city":"伊犁哈萨克","address":"新疆伊犁察布查尔县扎库齐牛录乡"},{"name":"温泉县呼和托哈供销社","code":"91652723229451678L","registrationDay":"1989-06-26","character":"集体所有制","legalRepresentative":"张定福","capital":"47万人民币","businessScope":"许可经营项目：无。一般经营项目：农副畜产品、化肥、农膜","province":"新疆","city":"博尔塔拉","address":"新疆博州温泉县呼和托哈种畜场"},{"name":"策勒县农村信用合作联社","code":"91653225230410400W","registrationDay":"1989-06-26","character":"N/A","legalRepresentative":"陈强","capital":"9,751.9141(万)","businessScope":"中国银监会核准的金融业务,房屋出租。","province":"新疆","city":"和田","address":"新疆和田地区策勒县托帕路2号"},{"name":"温泉县哈日布呼供销社","code":"9165272322945211XA","registrationDay":"1989-06-28","character":"集体所有制","legalRepresentative":"代军","capital":"67万人民币","businessScope":"食品饮料及烟草制品、纺织、服装及日用品、文化体育、办公用品、家用电器及电子产品、五金的销售；柜台出租。","province":"新疆","city":"博尔塔拉","address":"新疆博州温泉县哈日布呼镇"},{"name":"伊宁县墩麻扎供销合作社","code":"91654021673416051A","registrationDay":"1989-06-29","character":"集体所有制","legalRepresentative":"李德强","capital":"42.5万人民币","businessScope":"化肥、农膜、种子销售，百货、针纺、五金交电、土产品销售、畜产品销售、农副产品收购、非生产性旧物资回收、畜产品收购、房屋租赁、摊位租赁、建材销售。","province":"新疆","city":"伊犁哈萨克","address":"新疆伊犁州伊宁县墩麻扎镇税务所旁"},{"name":"第八师一五〇团加工一厂","code":"91659001722397126Q","registrationDay":"1989-06-29","character":"国有企业","legalRepresentative":"樊增建","capital":"N/A","businessScope":"籽棉加工，农作物机械收割，网套加工。","province":"新疆","city":"石河子","address":"新疆石河子市150团团部"},{"name":"精河县农村信用合作联社乌伊路信用社","code":"91652722929432697C","registrationDay":"1989-06-29","character":"N/A","legalRepresentative":"冯建强","capital":"N/A","businessScope":"经营中国银行业监督管理委员会依照有关法律、行政法规和其他规定批准的业务，经营范围以批准文件所列的为准；无。","province":"新疆","city":"博尔塔拉","address":"新疆博州精河县城镇伊犁路阳光美居1号楼"},{"name":"第八师一五〇团加工二厂","code":"916590017789514727","registrationDay":"1989-06-30","character":"国有企业","legalRepresentative":"郑文刚","capital":"N/A","businessScope":"籽棉加工，棉短绒加工，农作物机械收割。","province":"新疆","city":"石河子","address":"新疆石河子市150团一营部"},{"name":"和田县农村信用合作联社","code":"91653221230330902J","registrationDay":"1989-07-01","character":"N/A","legalRepresentative":"李明","capital":"8,179.3118(万)","businessScope":"许可经营项目：","province":"新疆","city":"和田","address":"新疆和田地区和田市迎宾路346号"},{"name":"和静县巴润哈尔莫墩供销社面粉加工厂","code":"9165282777036074XG","registrationDay":"1989-07-06","character":"集体分支机构(非法人)","legalRepresentative":"罗刚孝","capital":"N/A","businessScope":"小麦的来料加工出售，粮食收购，挂面加工出售","province":"新疆","city":"巴音郭楞","address":"新疆巴州和静县巴润哈尔莫墩镇"},{"name":"霍城县农村信用合作联社良繁场信用社","code":"9165402379819929XP","registrationDay":"1989-07-07","character":"N/A","legalRepresentative":"吴晓明","capital":"N/A","businessScope":"办理存款、贷款、票据贴现、国内结算业务；办理个人储蓄业务；代理其它银行的金融业务；代理收付款项及受托代办保险业务；买卖政府债券；代理发行、代理兑付、承销政府债券；提供保险箱服务；由县联社统一办理资金融通调剂业务；办理经中国银行业监督管理委员会批准的其他业务；房屋租赁。","province":"新疆","city":"伊犁哈萨克","address":"新疆伊犁州霍城县良繁场场部"},{"name":"拜城县军辉残疾人木材综合加工厂","code":"9165292662534417XY","registrationDay":"1989-07-08","character":"个人独资企业","legalRepresentative":"张军辉","capital":"N/A","businessScope":"许可经营项目：锯材加工。一般经营项目：木材、刨花板销售；木器综合加工、销售；秸秆成板加工、销售。","province":"新疆","city":"阿克苏","address":"新疆阿克苏地区拜城县托克逊乡阿娜克孜兰干"},{"name":"疏勒县供销联社","code":"91653122230080413J","registrationDay":"1989-07-10","character":"集体所有制","legalRepresentative":"巴拉提·亚库普","capital":"135万人民币","businessScope":"许可经营项目：（具体经营项目以有关部门批准文件或颁发的许可证件、资质证书为准）：预包装食品","province":"新疆","city":"喀什","address":"新疆喀什地区疏勒县胜利北路"},{"name":"第二师三十五团加工厂","code":"91652823929541500E","registrationDay":"1989-07-15","character":"N/A","legalRepresentative":"荆峰","capital":"N/A","businessScope":"籽棉加工。棉花收购。","province":"新疆","city":"巴音郭楞","address":"新疆巴州尉犁县农二师三十五团"},{"name":"克拉玛依一三六团联合加工厂","code":"91650200757681688P","registrationDay":"1989-07-20","character":"国有企业","legalRepresentative":"郭希海","capital":"N/A","businessScope":"食用植物油加工与销售；籽棉收购加工；网套加工。","province":"新疆","city":"克拉玛依","address":"新疆克拉玛依市一三六团团部"},{"name":"阿图什市农村信用合作联社","code":"916530017422377605","registrationDay":"1989-07-21","character":"N/A","legalRepresentative":"沈学军","capital":"1,206(万)","businessScope":"吸收公众存款；发放短期、中期和长期贷款；办理国内结算，办理票据承兑与贴现；代理发行、代理兑付、承销政府债券；从事同业拆借；办理银行卡业务","province":"新疆","city":"克孜勒苏柯尔克孜","address":"新疆克州阿图什市帕米尔路西2院(州水利局三楼)"},{"name":"尉犁县兴平供销社","code":"916528237668090141","registrationDay":"1989-07-21","character":"集体所有制","legalRepresentative":"蒋才勇","capital":"26万人民币","businessScope":"零售：化肥、有毒品","province":"新疆","city":"巴音郭楞","address":"新疆巴州尉犁县万和幸福步行街A4-108商铺"},{"name":"温宿县克孜勒镇基层供销社","code":"916529222297307497","registrationDay":"1989-07-22","character":"集体所有制","legalRepresentative":"张自力","capital":"63万人民币","businessScope":"农药","province":"新疆","city":"阿克苏","address":"新疆阿克苏地区温宿县克孜勒镇"},{"name":"玛纳斯县农村信用合作联社","code":"916523247155318337","registrationDay":"1989-07-27","character":"N/A","legalRepresentative":"程强","capital":"16,552.1851(万元人民币)","businessScope":"办理存款、贷款、票据贴现、国内结算业务；办理个人储蓄业务；代理其他银行的金融业务；代理收付款项及受托代办保险业务；代理发行；保管箱租赁；房屋租赁；黄金白银、珠宝首饰、工艺品销售；专户理财*。","province":"新疆","city":"昌吉","address":"新疆昌吉州玛纳斯县凤城西路87号"},{"name":"中国能源建设集团新疆电力设计院有限公司","code":"916501002286655353","registrationDay":"1989-08-03","character":"N/A","legalRepresentative":"阎智","capital":"15,000(万)","businessScope":"压力管道设计。工程勘察、工程设计、工程咨询、工程总承包，水土保持方案编制资格甲级，测绘甲级，水土保持监测资质乙级，消防设施专项工程设计，城乡规划编制，计算机信息系统集成，对外工程承包，货物与技术的进出口业务，水土保持设施验收技术评估，节能评估，自理报检","province":"新疆","city":"乌鲁木齐","address":"新疆乌鲁木齐市天山区三道湾路100号"},{"name":"塔城市也门勒基层供销社","code":"916542012307509747","registrationDay":"1989-08-12","character":"集体所有制","legalRepresentative":"李新乾","capital":"40万人民币","businessScope":"纺织品、百货、五金交电；棉麻土产品、日用杂品、中小农具、化肥、农用地膜、畜产品收购。","province":"新疆","city":"塔城","address":"新疆塔城地区塔城市也门勒乡"},{"name":"塔什库尔干县农村信用合作联社","code":"91653131710834544Y","registrationDay":"1989-08-15","character":"N/A","legalRepresentative":"胡达拜提·买买提","capital":"N/A","businessScope":"吸收公众存款、发放贷款、办理国内结算、票据贴现、代理其他银行的金融业务、代理收付款项及受托代办保险业务、代理发行、代理兑付、承销国债和政策性金融债卷；买卖国债和政策性金融债卷；按银监局规定并经中国人民银行批准进行从事同业拆借；提供保管箱服务；经银监局批准的其他业务。","province":"新疆","city":"喀什","address":"新疆喀什地区塔什库尔干县乔戈里路6号"},{"name":"巴楚县农村信用合作联社阿瓦提信用社","code":"91653130726961927R","registrationDay":"1989-08-21","character":"N/A","legalRepresentative":"努尔买海木·买海提","capital":"N/A","businessScope":"办理存款、贷款、票据贴现、国内结算业务、办理个人储蓄业务，代理其他银行的金融业务、买卖政府债券、代理收付款项及受托代办保险业务.代理发行、代理兑付、承销政府债券，提供保险箱业务；由县联社统一办理资金融通调剂业务；办理经中国银行业监督管理委员会批准的其他业务、房屋租赁。","province":"新疆","city":"喀什","address":"新疆喀什地区巴楚县阿瓦提镇"},{"name":"巴楚县农村信用合作联社色力布亚信用社","code":"91653130726961898E","registrationDay":"1989-08-21","character":"N/A","legalRepresentative":"吾买尔·沙来","capital":"N/A","businessScope":"许可经营项目：(具体经营项目以有关部门的批准或颁发的许可证、资质证书为准)办理存款、贷款、票据贴现、国内结算业务、办理个人储蓄业务，代理其他银行的金融业务、买卖政府债券、代理收付款项及受托代办保险业务.代理发行、代理兑付、承销政府债券，提供保险箱业务；由县联社统一办理资金融通调剂业务；办理经中国银行业监督管理委员会批准的其他业务。一般经营项目：(法律、行政法规有专项审批的除外)无。","province":"新疆","city":"喀什","address":"新疆喀什地区巴楚县色力布亚镇"},{"name":"巴楚县农村信用合作联社阿拉格尔信用社","code":"9165313072696188XE","registrationDay":"1989-08-21","character":"N/A","legalRepresentative":"阿布都艾尼·司马义","capital":"N/A","businessScope":"办理存款、贷款、票据贴现、国内结算业务、办理个人储蓄业务，代理其他银行的金融业务、买卖政府债券、代理收付款项及受托代办保险业务.代理发行、代理兑付、承销政府债券，提供保险箱业务；由县联社统一办理资金融通调剂业务；办理经中国银行业监督管理委员会批准的其他业务无。","province":"新疆","city":"喀什","address":"新疆喀什地区巴楚县阿拉格尔乡"},{"name":"巴楚县农村信用合作联社夏马勒信用社","code":"91653130726961863U","registrationDay":"1989-08-21","character":"N/A","legalRepresentative":"艾克巴尔·阿布里克木","capital":"N/A","businessScope":"办理存款、贷款、票据贴现、国内结算业务、办理个人储蓄业务，代理其他银行的金融业务、买卖政府债券、代理收付款项及受托代办保险业务.代理发行、代理兑付、承销政府债券，提供保险箱业务；由县联社统一办理资金融通调剂业务；办理经中国银行业监督管理委员会批准的其他业务。","province":"新疆","city":"喀什","address":"新疆喀什地区巴楚县夏马勒乡"},{"name":"巴楚县农村信用合作联社琼库恰克信用社","code":"916531307269619002","registrationDay":"1989-08-21","character":"N/A","legalRepresentative":"阿布杜瓦依提江·阿吾提","capital":"N/A","businessScope":"办理存款、贷款、票据贴现、国内结算业务、办理个人储蓄业务，代理其他银行的金融业务、买卖政府债券、代理收付款项及受托代办保险业务.代理发行、代理兑付、承销政府债券，提供保险箱业务；由县联社统一办理资金融通调剂业务；办理经中国银行业监督管理委员会批准的其他业务,房屋租赁。","province":"新疆","city":"喀什","address":"新疆喀什地区巴楚县琼库恰克乡"},{"name":"巴楚县农村信用合作联社阿克萨克马热勒信用社","code":"91653130726961871N","registrationDay":"1989-08-21","character":"N/A","legalRepresentative":"阿布都热合曼·吾布力","capital":"N/A","businessScope":"办理存款、贷款、票据贴现、国内结算业务、办理个人储蓄业务，代理其他银行的金融业务、买卖政府债券、代理收付款项及受托代办保险业务，代理发行、代理兑付、承销政府债券，提供保险箱业务；由县联社统一办理资金融通调剂业务；办理经中国银行业监督管理委员会批准的其他业务。","province":"新疆","city":"喀什","address":"新疆喀什地区巴楚县阿克萨克马热勒乡"},{"name":"巴楚县农村信用合作联社多来提巴格信用社","code":"916531307269618476","registrationDay":"1989-08-21","character":"N/A","legalRepresentative":"张大辉","capital":"N/A","businessScope":"办理存款、贷款、票据贴现、国内结算业务、办理个人储蓄业务，代理其他银行的金融业务、买卖政府债券、代理收付款项及受托代办保险业务.代理发行、代理兑付、承销政府债券，提供保险箱业务；由县联社统一办理资金融通调剂业务；办理经中国银行业监督管理委员会批准的其他业务。","province":"新疆","city":"喀什","address":"新疆喀什地区巴楚县多来提巴格乡"},{"name":"巴楚县农村信用合作联社阿纳库勒信用社","code":"916531307269618551","registrationDay":"1989-08-21","character":"N/A","legalRepresentative":"柔鲜古丽·图拉克","capital":"N/A","businessScope":"办理存款、贷款、票据贴现、国内结算业务、办理个人储蓄业务，代理其他银行的金融业务、买卖政府债券、代理收付款项及受托代办保险业务.代理发行、代理兑付、承销政府债券，提供保险箱业务；由县联社统一办理资金融通调剂业务；办理经中国银行业监督管理委员会批准的其他业务。","province":"新疆","city":"喀什","address":"新疆喀什地区巴楚县阿纳库勒乡"},{"name":"巴楚县农村信用合作联社英吾斯坦信用社","code":"91653130726961919Y","registrationDay":"1989-08-21","character":"N/A","legalRepresentative":"达吾提·阿布都外力","capital":"N/A","businessScope":"办理存款、贷款、票据贴现、国内结算业务、办理个人储蓄业务，代理其他银行的金融业务、买卖政府债券、代理收付款项及受托代办保险业务.代理发行、代理兑付、承销政府债券，提供保险箱业务；由县联社统一办理资金融通调剂业务；办理经中国银行业监督管理委员会批准的其他业务,房屋租赁。","province":"新疆","city":"喀什","address":"巴楚县英吾斯坦乡"},{"name":"巴楚县农村信用合作联社城镇信用社","code":"91653130726961820E","registrationDay":"1989-08-21","character":"N/A","legalRepresentative":"姑丽斯塔尼·色衣来","capital":"N/A","businessScope":"办理存款、贷款、票据贴现、国内结算业务、办理个人储蓄业务，代理其他银行的金融业务、买卖政府债券、代理收付款项及受托代办保险业务.代理发行、代理兑付、承销政府债券，提供保险箱业务；由县联社统一办理资金融通调剂业务；办理经中国银行业监督管理委员会批准的其他业务。","province":"新疆","city":"喀什","address":"新疆喀什地区巴楚县人民西路"},{"name":"新疆卧龙建筑机械厂","code":"916501096252176643","registrationDay":"1989-08-26","character":"普通合伙","legalRepresentative":"陈雪雏","capital":"N/A","businessScope":"建筑机械、新型暖气片、塑料制品、日用化工制造销售；水暖器材、二三类机电产品、橡胶制品、电线电缆、水泵、汽车配件、农机配件、建筑五金销售。","province":"新疆","city":"乌鲁木齐","address":"新疆乌鲁木齐市米东区铁厂沟镇林泉路2452号"},{"name":"沙湾县供销社综合贸易服务中心","code":"916542232308111919","registrationDay":"1989-08-26","character":"集体所有制","legalRepresentative":"薛卫东","capital":"139.2万人民币","businessScope":"日用百货，服务，鞋帽，针纺织品，日用杂品，文化用品，五金交电，建材，农副产品","province":"新疆","city":"塔城","address":"新疆塔城地区沙湾县广场路138号"},{"name":"且末县农村信用合作联社塔提让信用社","code":"91652825313341359G","registrationDay":"1989-09-01","character":"N/A","legalRepresentative":"李智强","capital":"N/A","businessScope":"许可经营项目：","province":"新疆","city":"巴音郭楞","address":"新疆巴州且末县塔提让乡政府旁"},{"name":"且末县农村信用合作联社阿克提坎墩信用社","code":"91652825313341412C","registrationDay":"1989-09-01","character":"N/A","legalRepresentative":"穆萨江·图尔荪","capital":"N/A","businessScope":"许可经营项目：","province":"新疆","city":"巴音郭楞","address":"新疆巴州且末县阿克提坎墩乡"},{"name":"且末县农村信用合作联社琼库勒信用社","code":"91652825313341164N","registrationDay":"1989-09-05","character":"N/A","legalRepresentative":"艾麦尔江·热伊木","capital":"N/A","businessScope":"许可经营项目：","province":"新疆","city":"巴音郭楞","address":"新疆巴州且末县琼库勒乡"},{"name":"且末县农村信用合作联社英吾斯塘信用社","code":"91652825313341287P","registrationDay":"1989-09-05","character":"N/A","legalRepresentative":"阿布都热西提·阿布都热依木","capital":"N/A","businessScope":"许可经营项目：","province":"新疆","city":"巴音郭楞","address":"新疆巴州且末县英吾斯塘乡"},{"name":"乌鲁木齐市头屯河区综合加工厂","code":"91650106228821278F","registrationDay":"1989-09-22","character":"股份合作制","legalRepresentative":"张延恒","capital":"5万人民币","businessScope":"房屋租赁。","province":"新疆","city":"乌鲁木齐","address":"新疆乌鲁木齐市头屯河区魏沪滩路73号"},{"name":"和田地区农资公司","code":"91653200676344620F","registrationDay":"1989-10-06","character":"集体所有制","legalRepresentative":"许前远","capital":"260万人民币","businessScope":"购销：化肥、农膜、农业机械及零配件、建材、畜产品、地毯、汽车零配件、服装鞋帽、房屋租赁、干鲜果品、小农具","province":"新疆","city":"和田","address":"新疆和田地区和田市迎宾路30号"},{"name":"和硕县农村信用合作联社马兰信用社","code":"916528287516898491","registrationDay":"1989-10-06","character":"N/A","legalRepresentative":"蒋红","capital":"N/A","businessScope":"办理存款、贷款、票据贴现、国内结算业务；办理个人储蓄业务；代理其他银行的金融业务；买卖政府债卷；代理发行、代理兑付、承销政府债卷；提供保险箱服务；由县联社统一办理资金融通调剂业务；办理经中国银行业监督管理委员会批准的其他业务。","province":"新疆","city":"巴音郭楞","address":"新疆巴州和硕县乌什塔拉乡马兰村"},{"name":"和硕县农村信用合作联社","code":"91652828229640612F","registrationDay":"1989-10-19","character":"N/A","legalRepresentative":"樊文萍","capital":"5,981.7500(万)","businessScope":"办理存款、贷款、票据贴现、国内结算业务；办理个人储蓄业务；代理其他银行的金融业务；买卖政府债券；代理发行、代理兑付、承销政府债券；提供保险箱服务；由县联社统一办理资金融通调剂业务；办理经中国银行业监督管理委员会批准的其他业务。","province":"新疆","city":"巴音郭楞","address":"新疆巴州和硕县文化二街"},{"name":"玛纳斯县农村信用合作联社下桥子信用社","code":"91652324660610250R","registrationDay":"1989-10-20","character":"N/A","legalRepresentative":"贾腾","capital":"N/A","businessScope":"办理存款、贷款、票据贴现、国内结算业务；办理个人储蓄业务；代理其他银行的金融业务；代理收付款项及受托代办保险业务；买卖政府债券；代理发行、代理兑付、承销政府债券；提供保险箱业务；由县联社统一办理资金融通调剂业务；办理经中国银行业监督管理委员会批准的其他业务*。","province":"新疆","city":"昌吉","address":"新疆昌吉州玛纳斯县兰州湾镇下桥子村"},{"name":"伽师县农村信用合作联社","code":"916531297155997901","registrationDay":"1989-10-25","character":"N/A","legalRepresentative":"呼中良","capital":"5,522.4945(万元人民币)","businessScope":"许可经营项目：办理存款、贷款、票据贴现、国内结算业务；办理个人储蓄业务；代理其他很行的金融业务；代理收付款项及受托代办保险业务；买卖政府债券；代理发行、代理兑付、承销政府债券；提供保险箱业务；由县联社统一办理资金融通调剂业务；办理经中国银行业监督管理委员会批准的其他业务。一般经营项目：房屋租赁。","province":"新疆","city":"喀什","address":"新疆喀什地区伽师县古宰尔西路14号"},{"name":"阿克陶县农村信用合作联社皮拉勒信用社","code":"91653022929943331N","registrationDay":"1989-11-04","character":"N/A","legalRepresentative":"阿吉古力·牙森","capital":"N/A","businessScope":"吸收公众存款；发放短期、中期和长期贷款；办理国内结算；办理票据承兑与贴现；代理发行、代理兑付、承销政府债券、金融债券；买卖政府债券；从事同业拆解；办理银行卡业务","province":"新疆","city":"克孜勒苏柯尔克孜","address":"新疆克州阿克陶县皮拉勒乡皮拉力路1007号"},{"name":"阿克陶县农村信用合作联社巴仁信用社","code":"9165302292994334XE","registrationDay":"1989-11-04","character":"N/A","legalRepresentative":"汪皓亮","capital":"N/A","businessScope":"金融业务、储蓄存款。","province":"新疆","city":"克孜勒苏柯尔克孜","address":"新疆克州阿克陶县巴仁乡"},{"name":"阿克陶县农村信用合作联社玉麦信用社","code":"91653022929943323U","registrationDay":"1989-11-04","character":"N/A","legalRepresentative":"莫合塔尔·阿不力米提","capital":"N/A","businessScope":"吸收公众存款；发放短期、中期和长期贷款；办理国内结算；办理票据承兑与贴现；代理发行、代理兑付、承销政府债券、金融债券；买卖政府债券；从事同业拆解；办理银行卡业务","province":"新疆","city":"克孜勒苏柯尔克孜","address":"新疆克州阿克陶县玉麦乡"},{"name":"阿克陶县农村信用合作联社营业部","code":"91653022929943446W","registrationDay":"1989-11-04","character":"N/A","legalRepresentative":"詹英","capital":"N/A","businessScope":"吸收公众存款；发放短期、中期和长期贷款；办理国内结算；办理票据承兑与贴现；代理发行、代理兑付、承销政府债券、金融债券；买卖政府债券；从事同业拆解；办理银行卡业务","province":"新疆","city":"克孜勒苏柯尔克孜","address":"新疆克州阿克陶县北大街140号"},{"name":"阿克陶县农村信用合作联社","code":"91653022229940586H","registrationDay":"1989-11-04","character":"N/A","legalRepresentative":"罗小虎","capital":"4,197.9900(万)","businessScope":"吸收公众存款；发放短期、中期和长期贷款；办理国内结算；办理票据承兑与贴现；代理发行、代理兑付、承销政府债券、金融债券；买卖政府债券；从事同业拆解；办理银行卡业务","province":"新疆","city":"克孜勒苏柯尔克孜","address":"新疆克州阿克陶县北大街140号"},{"name":"阿克陶县农村信用合作联社阿克陶镇信用社","code":"916530229299433151","registrationDay":"1989-11-04","character":"N/A","legalRepresentative":"布阿吉尔·司马义","capital":"N/A","businessScope":"吸收公众存款；发放短期、中期和长期贷款；办理国内结算；办理票据承兑与贴现；代理发行、代理兑付、承销政府债券、金融债券；买卖政府债券；从事同业拆解；办理银行卡业务","province":"新疆","city":"克孜勒苏柯尔克孜","address":"新疆克州阿克陶县人民东路46院2号"},{"name":"布尔津县农村信用合作联社","code":"91654321230940532P","registrationDay":"1989-11-08","character":"N/A","legalRepresentative":"吴俊辉","capital":"5,673.1289(万)","businessScope":"经营中国银行业监督管理委员会依照有关法律、行政法规和其他规定批准的业务，经营范围已批准文件为准。与贷款项目相关的财产保险、家财险、长期寿险、人身意外伤害险、健康险。","province":"新疆","city":"阿勒泰","address":"新疆阿勒泰地区布尔津县神湖路13号"},{"name":"库车县农村信用合作联社牙哈信用社","code":"91652923715591270Y","registrationDay":"1989-11-12","character":"N/A","legalRepresentative":"吐尔逊·艾依提","capital":"N/A","businessScope":"办理存、贷款、票据贴现、国内结算业务；办理个人储蓄业务；代理其他银行的金融业务；代理收付款项；买卖政府债券；代理发行、代理兑付、承销政府债券；提供保险箱服务；由县联社统一办理资金融通调剂业务；办理经中国银行业监督委员会批准的其他业务。","province":"新疆","city":"阿克苏","address":"新疆阿克苏地区库车县牙哈镇"},{"name":"托里县农村信用合作联社阿合别里斗信用社","code":"916542247760512354","registrationDay":"1989-11-16","character":"N/A","legalRepresentative":"李庆华","capital":"N/A","businessScope":"农牧民个人存、贷款服务。","province":"新疆","city":"塔城","address":"新疆塔城地区托里县阿合别斗乡"},{"name":"托里县农村信用合作联社库甫信用社","code":"91654224731803763J","registrationDay":"1989-11-16","character":"N/A","legalRepresentative":"沙丽肯·恰孜肯","capital":"N/A","businessScope":"存款,贷款业务。","province":"新疆","city":"塔城","address":"新疆塔城地区托里县库甫乡"},{"name":"托里县农村信用合作联社乌雪特信用社","code":"91654224731803771D","registrationDay":"1989-11-16","character":"N/A","legalRepresentative":"宫照波","capital":"N/A","businessScope":"存款,贷款业务。","province":"新疆","city":"塔城","address":"新疆塔城地区托里县乌雪特乡"},{"name":"和田县罕尔日克乡供销社","code":"91653221230330128R","registrationDay":"1989-11-22","character":"集体所有制","legalRepresentative":"阿布都热西提·阿瓦孜","capital":"72万人民币","businessScope":"农膜、化肥、干果、日用百货、纺织品、小五金、糖烟酒销售；畜产品收购、销售。","province":"新疆","city":"和田","address":"新疆和田地区和田县罕尔日克乡"},{"name":"中国邮政集团公司石河子市报刊批发零售门市部","code":"91659001MA776RQF0R","registrationDay":"1989-11-30","character":"N/A","legalRepresentative":"张磊","capital":"N/A","businessScope":"图书、报刊、杂志的销售。挂历,明信片的销售。","province":"新疆","city":"石河子","address":"新疆石河子市北四路1小区"},{"name":"塔什库尔干塔吉克自治县瓦恰二区供销社","code":"9165313123026006X8","registrationDay":"1989-12-15","character":"集体所有制","legalRepresentative":"夏巴孜·库力","capital":"19万人民币","businessScope":"日用百货、五金交电、文化用品、针织品、土特产品。","province":"新疆","city":"喀什","address":"新疆喀什地区塔什库尔干县瓦恰乡"}]}