{"erDataList":[{"name":"南洋航运集团股份有限公司","code":"91460000201289277G","registrationDay":"1989-01-27","character":"N/A","legalRepresentative":"王景","capital":"24,871.8129(万元人民币)","businessScope":"物流服务（运输除外）；仓储","province":"海南","city":"海口","address":"海南省海口市滨海大道81号南洋大厦2006、2007"},{"name":"海南天涯水业(集团)公司","code":"9146020070881929XE","registrationDay":"1989-01-29","character":"N/A","legalRepresentative":"袁文革","capital":"12,000(万元)","businessScope":"城市原水供应，自来水生产与销售，水电安装与维修，旅游开发，职工技术培训与咨询，水暖器材、五金交电、交电商业、机械产品的销售，房地产开发与经营(仅供办证使用)。","province":"海南","city":"三亚","address":"海南省三亚市河西区金鸡岭街336号"},{"name":"中国中丝集团海南公司","code":"91460000201285313N","registrationDay":"1989-01-30","character":"N/A","legalRepresentative":"于雷","capital":"20,000(万元人民币)","businessScope":"茧、丝、绸及其制成品、针纺织品及其制成品、化纤原料、染化料、纺织机械、皮革、皮革制品、木材、木制品进出口业务按(90)琼贸企业审字第16号文经营，五金工具、矿产品(专营除外)、仪器仪表、保健用品、化工产品(危险品除外)、家用电器、电子机械、建筑材料、土畜产品、工艺品、酒类、粮油、饲料、化肥、食糖、纸浆、钢材、通讯设备、电脑配件的销售。","province":"海南","city":"海口","address":"海口市龙昆北路国贸大厦A座9层"},{"name":"海南中实(集团)有限公司","code":"914600007088540441","registrationDay":"1989-03-20","character":"N/A","legalRepresentative":"方志亮","capital":"18,000(万元)","businessScope":"自有房屋租赁，农业项目投资开发，房地产投资，房地产信息咨询，室内外装饰装修工程施工，化工原料","province":"海南","city":"海口","address":"海口市龙华区滨海大道81号南洋大厦11层"},{"name":"儋州市番加供销社副食、针纺门市部","code":"91469003MA5REPWF1Q","registrationDay":"1989-04-09","character":"N/A","legalRepresentative":"曾瑞龙","capital":"N/A","businessScope":"糖、烟、酒、针纺、副食。","province":"海南","city":"儋州","address":"儋州市番加乡"},{"name":"汕头市建安(集团)公司海南分公司","code":"9146000020126001XJ","registrationDay":"1989-04-10","character":"N/A","legalRepresentative":"吴惜全","capital":"N/A","businessScope":"房屋建筑工程，市政公用工程，建筑装修装饰工程，机电设备安装工程，体育场地设施工程，地基与基础工程，钢结构工程。","province":"海南","city":"海口","address":"海口市华海路东海住宅区3121-3222号"},{"name":"临高县供销社贸易公司","code":"91469028201560805E","registrationDay":"1989-04-20","character":"集体所有制","legalRepresentative":"方朝阳","capital":"85万人民币","businessScope":"农副产品购销、食盐、灯用煤油、柴油、废旧物资回收、化学肥料、化学农药、农膜、干鲜蔬菜。","province":"海南","city":"省直辖县","address":"临高县临城镇解放路"},{"name":"儋州市海头供销社文具五金门市部","code":"91469003MA5RC35H5L","registrationDay":"1989-04-29","character":"集体分支机构(非法人)","legalRepresentative":"叶凌波","capital":"N/A","businessScope":"日杂，土产，日用百货，针织，化肥","province":"海南","city":"儋州","address":"儋州市海头镇"},{"name":"儋州市海头供销社","code":"914690039015822205","registrationDay":"1989-04-29","character":"集体分支机构(非法人)","legalRepresentative":"陈炜","capital":"N/A","businessScope":"日杂、土产、日用百货、针织、化肥。","province":"海南","city":"儋州","address":"儋州市海头镇"},{"name":"儋州市海头供销社第二综合门市部","code":"91469003MA5RFNU57U","registrationDay":"1989-04-29","character":"集体分支机构(非法人)","legalRepresentative":"林浩虎","capital":"N/A","businessScope":"针棉织、日用百货、五金交电销售。","province":"海南","city":"儋州","address":"儋州市海头镇"},{"name":"三亚大东山海洋养殖有限公司六道养殖场","code":"914602007088197246","registrationDay":"1989-05-10","character":"分公司","legalRepresentative":"吕梁鉴","capital":"N/A","businessScope":"养殖鲍鱼、月光螺、贝类","province":"海南","city":"三亚","address":"海南省三亚市田独镇六道湾量村"},{"name":"茂名市建筑集团有限公司海南分公司","code":"91460000201259449P","registrationDay":"1989-06-26","character":"N/A","legalRepresentative":"李勇","capital":"N/A","businessScope":"承接：建筑、设备安装、非标制作、水电安装、装饰、消防、空调制冷、电梯、公路桥梁工程","province":"海南","city":"海口","address":"海口市金贸西路8号诚田花园(诚田商务大厦A座11C)"},{"name":"万宁市三更罗供销合作社","code":"91469006201488022L","registrationDay":"1989-07-26","character":"集体所有制","legalRepresentative":"王天才","capital":"238.6万人民币","businessScope":"化肥、农膜、农副产品、建材、针棉织品、百货、日什、五金、化工原料、糖烟酒、预包装兼散食品、文具、图书、柴油、煤油、水产品、水果、乳制品(含婴幼配方乳粉)、儿童玩具","province":"海南","city":"省直辖县","address":"海南省万宁市三更罗镇"},{"name":"万宁市三更罗供销合作社加油站","code":"91469006747768704Y","registrationDay":"1989-07-28","character":"私营企业","legalRepresentative":"张春花","capital":"3万人民币","businessScope":"成品油零售。","province":"海南","city":"省直辖县","address":"海南省万宁市三更罗镇"},{"name":"万宁市三更罗供销合作社新中综合二门市部","code":"91469006MA5RFPB511","registrationDay":"1989-07-28","character":"私营企业","legalRepresentative":"蔡兴隆","capital":"0.5万人民币","businessScope":"针织品、百货零售。","province":"海南","city":"省直辖县","address":"海南省万宁市三更罗镇"},{"name":"万宁市三更罗供销合作社新中批发部","code":"914690066651152838","registrationDay":"1989-07-28","character":"私营企业","legalRepresentative":"官升平","capital":"1.5万人民币","businessScope":"预包装兼散装食品、烟、百货、日什零售；（凡需行政许可的项目需凭许可证经营）","province":"海南","city":"省直辖县","address":"海南省万宁市三更罗镇"},{"name":"万宁市三更罗供销合作社香根购销站","code":"91469006665115240T","registrationDay":"1989-07-29","character":"私营企业","legalRepresentative":"黄辉","capital":"3万人民币","businessScope":"百货、棉布、棉制品、日杂零售。","province":"海南","city":"省直辖县","address":"海南省万宁市三更罗镇"},{"name":"万宁市三更罗供销合作社建材综合门市部","code":"91469006665115259P","registrationDay":"1989-07-29","character":"私营企业","legalRepresentative":"陈孟军","capital":"1万人民币","businessScope":"建材、水泥、石灰零售。","province":"海南","city":"省直辖县","address":"海南省万宁市三更罗镇"},{"name":"万宁市三更罗供销合作社新中百货综合门市部","code":"91469006665115304Q","registrationDay":"1989-07-29","character":"私营企业","legalRepresentative":"林赞东","capital":"2万人民币","businessScope":"百货、棉布、棉织品零售。","province":"海南","city":"省直辖县","address":"海南省万宁市新中农场"},{"name":"万宁市三更罗供销合作社新中日杂五金综合门市部","code":"91469006665115267J","registrationDay":"1989-07-29","character":"私营企业","legalRepresentative":"陈传学","capital":"1万人民币","businessScope":"农药","province":"海南","city":"省直辖县","address":"海南省万宁市三更罗镇"},{"name":"三亚南新实业集团有限公司","code":"914602002013479917","registrationDay":"1989-08-01","character":"N/A","legalRepresentative":"钟路","capital":"10,000(万元)","businessScope":"房地产开发，房产销售，物业管理，仓储服务","province":"海南","city":"三亚","address":"海南省三亚市吉阳区荔枝沟路868号南新农场办公楼"},{"name":"文昌市东阁供销社加油站","code":"91469005742585263W","registrationDay":"1989-08-14","character":"私营企业","legalRepresentative":"林明强","capital":"25万人民币","businessScope":"柴油、汽油、煤油、机油。","province":"海南","city":"省直辖县","address":"文昌市东阁镇"},{"name":"文昌市东阁供销社","code":"9146900520144808X1","registrationDay":"1989-08-16","character":"集体所有制","legalRepresentative":"林明强","capital":"67万人民币","businessScope":"农业生产资料、百货、糖烟酒、针织品、杂货、五金交电、化工、医药、饮食、柴油、煤油、建材、汽油。","province":"海南","city":"省直辖县","address":"文昌市东阁镇"},{"name":"广西建工集团第二建筑工程有限责任公司海南分公司","code":"914600002012560299","registrationDay":"1989-08-22","character":"N/A","legalRepresentative":"罗世坤","capital":"N/A","businessScope":"工业与民用建筑、市政水电、卫生、通风空调、工业设备安装；建筑幕墙；高级装饰；挖孔桩。","province":"海南","city":"海口","address":"海口市南宝路26号双南居室D座三楼"},{"name":"中铁大桥局集团有限公司海南分公司","code":"91460000201256360J","registrationDay":"1989-09-06","character":"N/A","legalRepresentative":"汤利华","capital":"N/A","businessScope":"混凝土构件、建筑材料、机械设备。","province":"海南","city":"海口","address":"海口市文联路38号"},{"name":"文昌市新桥供销社大昌百货门市部","code":"91469005793130648C","registrationDay":"1989-09-07","character":"私营企业","legalRepresentative":"林尤其","capital":"2.5万人民币","businessScope":"百货、针纺织品、家用电器。","province":"海南","city":"省直辖县","address":"新桥大昌圩"},{"name":"文昌市新桥供销社五金门市","code":"9146900579313063XC","registrationDay":"1989-09-07","character":"私营企业","legalRepresentative":"吴多壮","capital":"2.9万人民币","businessScope":"五金、交电、化工。","province":"海南","city":"省直辖县","address":"新桥镇"},{"name":"文昌市新桥供销社百货门市部","code":"91469005793130680P","registrationDay":"1989-09-07","character":"私营企业","legalRepresentative":"龙宝","capital":"3.4万人民币","businessScope":"百货、针纺织品、家用电器。","province":"海南","city":"省直辖县","address":"新桥镇"},{"name":"文昌市罗豆供销社","code":"91469005201448186F","registrationDay":"1989-09-08","character":"集体所有制","legalRepresentative":"韩任元","capital":"142万人民币","businessScope":"百货、针纺、五金交电、化工、糖烟酒、副食、生产资料、土杂、煤油、建材、农副产品。","province":"海南","city":"省直辖县","address":"文昌市罗豆圩"},{"name":"万宁市后安供销合作社","code":"91469006201488444K","registrationDay":"1989-09-15","character":"集体所有制","legalRepresentative":"官宏平","capital":"27万人民币","businessScope":"日用百货、针织、五金、文具、农业生产资料、购销农村产品、棉布。","province":"海南","city":"省直辖县","address":"万宁市后安墟"},{"name":"文昌市龙马供销社","code":"91469005201448282Q","registrationDay":"1989-09-16","character":"集体所有制","legalRepresentative":"林岩","capital":"110万人民币","businessScope":"日用百货、针棉织品、日杂、土产、烟酒、副食、五金交电、文具、医药、生产资料(除专营外)、农副产品(以上项目仅限于分支机构经营)。","province":"海南","city":"省直辖县","address":"文昌市龙马圩"},{"name":"文昌市文城供销社综合货亭","code":"91469005793118235M","registrationDay":"1989-09-18","character":"集体分支机构(非法人)","legalRepresentative":"何秋月","capital":"N/A","businessScope":"百货、酒、饮料、副食品，保健食品销售。","province":"海南","city":"省直辖县","address":"文昌市文城镇白芒村何秋月宅"},{"name":"文昌市重兴供销社第二百货门市部","code":"91469005774294903R","registrationDay":"1989-09-20","character":"私营企业","legalRepresentative":"陈奕能","capital":"1.8万人民币","businessScope":"百货、针纺织品、文具、销售。","province":"海南","city":"省直辖县","address":"文昌市重兴镇"},{"name":"文昌市重兴供销社二货亭","code":"914690057742947005","registrationDay":"1989-09-20","character":"私营企业","legalRepresentative":"欧兰花","capital":"1.2万人民币","businessScope":"百货、日杂、销售。","province":"海南","city":"省直辖县","address":"文昌市重兴镇"},{"name":"文昌市重兴供销社仙昌百货门市部","code":"91469005774294639E","registrationDay":"1989-09-20","character":"私营企业","legalRepresentative":"叶世冠","capital":"1.2万人民币","businessScope":"针纺织品、洗涤用品、百货、销售。","province":"海南","city":"省直辖县","address":"文昌市重兴镇仙昌圩"},{"name":"文昌市重兴供销社土什门市部","code":"91469005774294911L","registrationDay":"1989-09-20","character":"私营企业","legalRepresentative":"李艳山","capital":"2.8万人民币","businessScope":"百货、土杂、日什、烟花炮竹。","province":"海南","city":"省直辖县","address":"文昌市重兴镇"},{"name":"文昌市重兴供销社第二副食门市部","code":"9146900577429468XH","registrationDay":"1989-09-20","character":"私营企业","legalRepresentative":"林方敏","capital":"1.2万人民币","businessScope":"糖烟酒、副食品、水果、预包装食品、乳制品","province":"海南","city":"省直辖县","address":"文昌市重兴镇"},{"name":"文昌市重兴供销社竹林副食门市部","code":"91469005MA5RG88B00","registrationDay":"1989-09-20","character":"私营企业","legalRepresentative":"符兴和","capital":"1.2万人民币","businessScope":"糖烟酒、副食品、小百货、预包装食品兼散装食品、乳制品","province":"海南","city":"省直辖县","address":"文昌市重兴镇竹林圩"},{"name":"文昌市重兴供销社第三副食门市部","code":"91469005774294663Y","registrationDay":"1989-09-20","character":"私营企业","legalRepresentative":"邢增民","capital":"1.2万人民币","businessScope":"副食品、糖烟酒、烟花炮竹、预包装食品兼散装食品、乳制品","province":"海南","city":"省直辖县","address":"文昌市重兴镇"},{"name":"文昌市重兴供销社纱布门市部","code":"914690057742949467","registrationDay":"1989-09-20","character":"私营企业","legalRepresentative":"陈奕武","capital":"1.2万人民币","businessScope":"副食、糖烟酒、针纺织品、百货，烟花爆竹，预包装食品兼散装食品、乳制品","province":"海南","city":"省直辖县","address":"文昌市重兴镇"},{"name":"文昌市重兴供销社第一副食门市部","code":"91469005774294698H","registrationDay":"1989-09-20","character":"私营企业","legalRepresentative":"庄光焕","capital":"1.2万人民币","businessScope":"糖烟酒、副食品、预包装食品兼散装食品乳制品","province":"海南","city":"省直辖县","address":"文昌市重兴镇"},{"name":"文昌市重兴供销社第二综合门市部","code":"91469005798749546P","registrationDay":"1989-09-20","character":"私营企业","legalRepresentative":"林斯儒","capital":"1.8万人民币","businessScope":"百货、针纺织品、家具、交电、日什。","province":"海南","city":"省直辖县","address":"文昌市重兴镇"},{"name":"万宁市港北供销合作社和乐推销组","code":"91469006MA5RFPE50Y","registrationDay":"1989-09-25","character":"私营企业","legalRepresentative":"吴关连","capital":"2.5万人民币","businessScope":"五交化、农机具。(凡需行政许可的项目凭许可证经营)","province":"海南","city":"省直辖县","address":"海南省万宁县和乐镇"},{"name":"万宁市东澳供销合作社","code":"91469006201488145M","registrationDay":"1989-09-25","character":"集体所有制","legalRepresentative":"吴焕雄","capital":"31万人民币","businessScope":"百货、针棉织品、土产、五金化工、五金交电、日杂、化肥、农膜、文化用品。","province":"海南","city":"省直辖县","address":"万宁市东澳镇"},{"name":"中金鹰(海南)安保集团有限公司","code":"914600002012905853","registrationDay":"1989-09-27","character":"N/A","legalRepresentative":"黎开明","capital":"2,000(万元)","businessScope":"保安服务、保安培训、保安装备、保安装署、防盗、防火、报警、通讯器材设计及安装,保养、维修安全技术防范设施工程和安全防范咨询、文化产业投资。","province":"海南","city":"海口","address":"海口市龙华区海秀中路96号海南奥林匹克花园8#、9#商场2"},{"name":"文昌市重兴供销社五金门市部","code":"91469005774294807G","registrationDay":"1989-09-30","character":"私营企业","legalRepresentative":"符第","capital":"1.8万人民币","businessScope":"五交电、化工材料、建材、装修材料、煤油。","province":"海南","city":"省直辖县","address":"文昌市重兴镇"},{"name":"文昌市潭牛供销社日杂门市","code":"91469005567969875A","registrationDay":"1989-10-04","character":"私营企业","legalRepresentative":"黄玉超","capital":"1.6万人民币","businessScope":"日杂、土产、陶器、建材、炮竹、煤油。","province":"海南","city":"省直辖县","address":"文昌市潭牛镇"},{"name":"文昌市潭牛供销社第二综合门市","code":"914690055679699473","registrationDay":"1989-10-06","character":"私营企业","legalRepresentative":"韩云","capital":"0.8万人民币","businessScope":"五交化、家用电器、钢材、水管、自来水配件、零件。","province":"海南","city":"省直辖县","address":"文昌市潭牛镇"},{"name":"文昌市潭牛供销社第六综合门市","code":"9146900556796998XB","registrationDay":"1989-10-09","character":"私营企业","legalRepresentative":"梁振锦","capital":"1万人民币","businessScope":"百货、日杂、针织。","province":"海南","city":"省直辖县","address":"文昌市潭牛镇"},{"name":"文昌市潭牛供销社文医门市","code":"914690055679698835","registrationDay":"1989-10-09","character":"私营企业","legalRepresentative":"林尤法","capital":"1.6万人民币","businessScope":"文具、图书。","province":"海南","city":"省直辖县","address":"文昌市潭牛镇"},{"name":"文昌市潭牛供销社第五综合门市","code":"91469005567969963Q","registrationDay":"1989-10-09","character":"私营企业","legalRepresentative":"韩冠元","capital":"0.7万人民币","businessScope":"糖烟酒、副食、百货。","province":"海南","city":"省直辖县","address":"文昌市潭牛镇"},{"name":"文昌市潭牛供销社第三综合门市","code":"91469005567969912G","registrationDay":"1989-10-09","character":"私营企业","legalRepresentative":"符爱蛾","capital":"1万人民币","businessScope":"糖烟酒、副食、日用百货、炮竹。","province":"海南","city":"省直辖县","address":"文昌市潭牛镇"},{"name":"文昌市潭牛供销社生产门市","code":"91469005MA5RG16P3P","registrationDay":"1989-10-09","character":"私营企业","legalRepresentative":"韩潮光","capital":"3万人民币","businessScope":"农业生产资料、化肥、日杂、土产。","province":"海南","city":"省直辖县","address":"文昌市潭牛镇"},{"name":"文昌市潭牛供销社生产经销部","code":"914690055679698910","registrationDay":"1989-10-09","character":"私营企业","legalRepresentative":"黎行天","capital":"2万人民币","businessScope":"农业生产资料、化肥、农用工具、水稻杂优种子销售。","province":"海南","city":"省直辖县","address":"文昌市潭牛镇"},{"name":"文昌市潭牛供销社八综合门市","code":"91469005MA5RG84138","registrationDay":"1989-10-09","character":"私营企业","legalRepresentative":"许环告","capital":"1万人民币","businessScope":"百货、针织、纺织、五交化、家用电器、文具。","province":"海南","city":"省直辖县","address":"文昌市潭牛镇"},{"name":"文昌市潭牛供销社针纺门市","code":"914690055679699398","registrationDay":"1989-10-09","character":"私营企业","legalRepresentative":"符艳芬","capital":"2.8万人民币","businessScope":"针织、纺织、百货、日杂。","province":"海南","city":"省直辖县","address":"文昌市潭牛镇"},{"name":"文昌市潭牛供销社综合经营部","code":"91469005567969904M","registrationDay":"1989-10-09","character":"私营企业","legalRepresentative":"范高法","capital":"5万人民币","businessScope":"饲料、建材。","province":"海南","city":"省直辖县","address":"文昌市潭牛镇"},{"name":"文昌市潭牛供销社五金门市","code":"91469005567969920B","registrationDay":"1989-10-09","character":"私营企业","legalRepresentative":"洪以雄","capital":"3.3万人民币","businessScope":"五金交电、化工、家用电器、煤油、机油。","province":"海南","city":"省直辖县","address":"文昌市潭牛镇"},{"name":"文昌市东郊供销社华龙家私城","code":"91469005MA5RG16258","registrationDay":"1989-10-10","character":"私营企业","legalRepresentative":"符思剑","capital":"0.2万人民币","businessScope":"针纺织品、百货、五交化、家用电器、家具、土产日杂、销售。","province":"海南","city":"省直辖县","address":"文昌市东郊镇"},{"name":"文昌市东郊供销社博仁文医门市","code":"91469005793149832W","registrationDay":"1989-10-10","character":"私营企业","legalRepresentative":"林师锐","capital":"4万人民币","businessScope":"百货、针织品、成衣、水产饲料、五交化家用电器、非处方药、处方药、中药材、中药饮片、中成药、化学药制剂、抗生素制剂销售。","province":"海南","city":"省直辖县","address":"文昌市东郊镇"},{"name":"海口速安运输有限公司","code":"914601002013062259","registrationDay":"1989-10-16","character":"有限责任公司","legalRepresentative":"黎辉电","capital":"300万人民币","businessScope":"出租车客运，","province":"海南","city":"海口","address":"海口市白龙乡美舍下村279号"},{"name":"海南华昌企业集团公司","code":"9146000020128904X6","registrationDay":"1989-10-18","character":"N/A","legalRepresentative":"胡明武","capital":"5,000(万元人民币)","businessScope":"生产，销售电子产品，家用电器(三包)，机电产品(不含汽车)，橡胶制品，汽车配件，纺织品，服装，五金工具， 化工产品(不含专营商品)，包装及印刷器材料，农副土特产品，日用百货，建筑材料， 矿产品(国家专营除外)。","province":"海南","city":"海口","address":"海口市龙华区玉沙路28号宝发国际大厦9层904房"},{"name":"定安县永丰供销合作社","code":"91469025201501717D","registrationDay":"1989-10-18","character":"集体所有制","legalRepresentative":"陈明靖","capital":"44万人民币","businessScope":"百货、烟酒、副食、针纺织品、农业生产资料、化工产品（专营除外）、五金交电、农副产品、废旧物资回收、文具、烟花炮竹","province":"海南","city":"省直辖县","address":"定安县龙湖镇永丰墟"},{"name":"文昌市龙楼供销社第一副食门市","code":"91469005793120079Q","registrationDay":"1989-10-23","character":"私营企业","legalRepresentative":"林洪岑","capital":"0.9万人民币","businessScope":"糖烟酒、副食、日用百货、销售。","province":"海南","city":"省直辖县","address":"文昌市龙楼镇"},{"name":"定安县翰林供销合作社","code":"914690252015051442","registrationDay":"1989-10-24","character":"集体所有制","legalRepresentative":"陈运清","capital":"50万人民币","businessScope":"五金交电、化工、百货、糖烟酒、土杂、副食、纱布、农业生产资料、建材、废旧物资、农副产品收购、饮食服务","province":"海南","city":"省直辖县","address":"翰林镇"},{"name":"定安县龙州供销社","code":"914690252015001086","registrationDay":"1989-10-25","character":"集体所有制","legalRepresentative":"陈显炳","capital":"20万人民币","businessScope":"农业生产资料、副食、针纺织品、土产、农副产品、百货、五金交电、日杂、化工产品","province":"海南","city":"省直辖县","address":"定安县龙州墟"},{"name":"定安县龙州供销社生产资料门市部","code":"91469025MA5RFNQD7Y","registrationDay":"1989-11-01","character":"集体分支机构(非法人)","legalRepresentative":"陈显炳","capital":"N/A","businessScope":"化肥、农具、农膜的零售。","province":"海南","city":"省直辖县","address":"龙州圩"},{"name":"广西建工集团第三建筑工程有限责任公司海南分公司","code":"914600002012574009","registrationDay":"1989-11-03","character":"N/A","legalRepresentative":"林亚秋","capital":"N/A","businessScope":"可承担24层以下的房屋建筑(壹级)，水电设备安装，装饰装修，木制品加工，建筑装修装饰，机械设备安装，建筑材料，普通机械。","province":"海南","city":"海口","address":"海口市海垦路118号绿谷康都6栋2单元505号房"},{"name":"文昌市冯坡供销社","code":"914690052014486102","registrationDay":"1989-11-06","character":"集体所有制","legalRepresentative":"吴清春","capital":"37万人民币","businessScope":"自由房屋租赁，日用百货、日用杂品、糖烟酒、副食、针棉织品、五金交电、家用电器、中西成药、生产资料、建材、煤油、柴油、机油、饲料、机电器械、农副产品收购。","province":"海南","city":"省直辖县","address":"文昌市冯坡镇"},{"name":"三亚市林旺供销社","code":"91460200201348417C","registrationDay":"1989-11-06","character":"集体所有制","legalRepresentative":"蔡亲春","capital":"78万人民币","businessScope":"废旧物品、棉布、针纺织品、百货、副食品、日什、五交化、文具、畜产品、野生动物（除受国家保护的外）、农副产品、化肥、农药、农具、农用薄膜、农用机械","province":"海南","city":"三亚","address":"海南省三亚市海棠湾镇林旺社区198号"},{"name":"三亚市林旺供销社下丈购销站","code":"91460200MA5RFQ724U","registrationDay":"1989-11-06","character":"私营企业","legalRepresentative":"王东升","capital":"0万人民币","businessScope":"废旧物品、棉布、针纺织品、百货、副食品、日什、五交化、文具、畜产品、野生动物（除受国家保护的外）、农副产品、化肥、农药、农具、农用薄膜、农用机械","province":"海南","city":"三亚","address":"三亚市林旺镇下丈乡"},{"name":"文昌市迈号供销社五金门市部","code":"914690056651194959","registrationDay":"1989-11-06","character":"私营企业","legalRepresentative":"符雄","capital":"1.8万人民币","businessScope":"五金、交电、化工、家用电器、日杂","province":"海南","city":"省直辖县","address":"文昌市迈号镇"},{"name":"文昌市南阳供销社","code":"91469005201448629Y","registrationDay":"1989-11-09","character":"集体所有制","legalRepresentative":"陈泽强","capital":"20万人民币","businessScope":"百货、针纺织品、五金交电、日杂、农副产品、农业生产资料、图书。","province":"海南","city":"省直辖县","address":"文昌市南阳镇"},{"name":"文昌市翁田供销社","code":"91469005201448645L","registrationDay":"1989-11-09","character":"集体所有制","legalRepresentative":"云大岛","capital":"48万人民币","businessScope":"农业生产资料、百货、针织品、图书文具、日杂。","province":"海南","city":"省直辖县","address":"文昌市翁田镇"},{"name":"文昌市翁田供销社土杂门市部","code":"91469005MA5RG8AH2P","registrationDay":"1989-11-09","character":"私营企业","legalRepresentative":"梁红英","capital":"1万人民币","businessScope":"日杂、土杂、炮竹、小农具、煤油、百货。","province":"海南","city":"省直辖县","address":"文昌市翁田镇"},{"name":"琼中黎族苗族自治县黎母山供销社","code":"914690362017211976","registrationDay":"1989-11-29","character":"集体所有制","legalRepresentative":"胡家雄","capital":"28万人民币","businessScope":"农业生产资料、日杂、糖烟酒、副食、针棉织品、五金交电、饮食、农副产品、百货。","province":"海南","city":"省直辖县","address":"琼中县黎母山镇"},{"name":"文昌市清澜供销社盼盼文体商店","code":"91469005MA5RG89A9G","registrationDay":"1989-11-29","character":"私营企业","legalRepresentative":"林日强","capital":"2.5万人民币","businessScope":"图书、文具、体育用品、百货、纺织品、五交电、国产卷烟。","province":"海南","city":"省直辖县","address":"文城镇清澜办事处渔港路"},{"name":"文昌市清澜供销社博仁安康药店","code":"914690050905325366","registrationDay":"1989-11-29","character":"私营企业","legalRepresentative":"王茀民","capital":"3.3万人民币","businessScope":"非处方药；处方药；中成药；化学药制剂；抗生素制剂；保健食品，预包装食品、乳制品","province":"海南","city":"省直辖县","address":"文昌市清澜镇"},{"name":"文昌市抱罗供销社","code":"91469005201448717D","registrationDay":"1989-12-01","character":"集体所有制","legalRepresentative":"王奋","capital":"112万人民币","businessScope":"农业生产资料、土杂、日杂、副食、糖烟酒、百货、针纺织品、五交化、成药、家具、家用电器、水泥、钢材、木材、竹藤。","province":"海南","city":"省直辖县","address":"文昌市抱罗镇"},{"name":"海口琼山红城日用厂","code":"914601002014203784","registrationDay":"1989-12-04","character":"集体所有制","legalRepresentative":"徐新阳","capital":"35.9万人民币","businessScope":"算盘。","province":"海南","city":"海口","address":"海口市琼山区府城镇文庄路16号"},{"name":"文昌市会文供销社会文纱布二门市","code":"91469005MA5RG86082","registrationDay":"1989-12-07","character":"私营企业","legalRepresentative":"梁俊德","capital":"2.5万人民币","businessScope":"纱布、针织、百货、烟。","province":"海南","city":"省直辖县","address":"会文镇"},{"name":"文昌市会文供销社冠南二百货门市","code":"91469005MA5RG16T64","registrationDay":"1989-12-07","character":"私营企业","legalRepresentative":"符史波","capital":"1.5万人民币","businessScope":"百货、针织、纱布、日杂、文具。","province":"海南","city":"省直辖县","address":"会文镇冠南圩"},{"name":"文昌市会文供销社白延烟酒门市","code":"91469005MA5RG8BQ2L","registrationDay":"1989-12-07","character":"私营企业","legalRepresentative":"林斯干","capital":"2.3万人民币","businessScope":"五交化、柴、煤油、日杂。","province":"海南","city":"省直辖县","address":"会文镇白延圩"},{"name":"文昌市铺前供销社东坡生产门市部","code":"91469005MA5RG1676G","registrationDay":"1989-12-11","character":"私营企业","legalRepresentative":"潘朝阳","capital":"3万人民币","businessScope":"农业生产资料、日用土杂。","province":"海南","city":"省直辖县","address":"文昌市铺前镇东坡圩"},{"name":"文昌市铺前供销社第二影相室","code":"91469005069669626Q","registrationDay":"1989-12-11","character":"私营企业","legalRepresentative":"韩干波","capital":"0.5万人民币","businessScope":"照相业、文化、文具、玩具、日用品、烟、鞋类、服装织品、副食品、销售。","province":"海南","city":"省直辖县","address":"文昌市铺前镇胜利街116号"},{"name":"文昌市铺前供销社纱布门市部","code":"91469005780704489Q","registrationDay":"1989-12-11","character":"私营企业","legalRepresentative":"陈有光","capital":"3万人民币","businessScope":"针纺织品、日用百货、家用电器、日用土杂零售、批发，香烟零售。","province":"海南","city":"省直辖县","address":"文昌市铺前镇昌华路"},{"name":"文昌市铺前供销社隆丰百货门市部","code":"91469005793135043Y","registrationDay":"1989-12-11","character":"私营企业","legalRepresentative":"潘向珠","capital":"4.3万人民币","businessScope":"日用百货、针纺织品、文化用品、五交化、日用土什、烟酒。","province":"海南","city":"省直辖县","address":"文昌市铺前镇隆丰圩"},{"name":"文昌市铺前供销社隆丰副食门市部","code":"91469005793134972T","registrationDay":"1989-12-11","character":"私营企业","legalRepresentative":"何敦章","capital":"1.5万人民币","businessScope":"果菜、副食、糖烟酒、日用土杂、小五金、文化用品、小百货、煤油、销售。","province":"海南","city":"省直辖县","address":"文昌市铺前镇隆丰圩"},{"name":"文昌市铺前供销社二综合门市部","code":"914690057931348927","registrationDay":"1989-12-11","character":"私营企业","legalRepresentative":"陈泽云","capital":"3.9万人民币","businessScope":"百货、日杂、五交化、家具、烟酒、文化用品、煤油。","province":"海南","city":"省直辖县","address":"文昌市铺前镇昌华路1号"},{"name":"文昌市铺前供销社二五金门市部","code":"91469005780704497K","registrationDay":"1989-12-11","character":"私营企业","legalRepresentative":"林旭晓","capital":"2万人民币","businessScope":"五交化、钢材、家用电器、煤油、日用土什、水果。","province":"海南","city":"省直辖县","address":"文昌市铺前镇昌华路"},{"name":"文昌市铺前供销社百货门市部","code":"9146900579313493XA","registrationDay":"1989-12-11","character":"私营企业","legalRepresentative":"卢方民","capital":"3万人民币","businessScope":"日用百货、针棉织品、家用电器、日用土杂、家俱、摩托车、燃气炉具、烟酒。","province":"海南","city":"省直辖县","address":"文昌市铺前镇昌华路"},{"name":"文昌市铺前供销社经理部","code":"91469005793135019E","registrationDay":"1989-12-11","character":"私营企业","legalRepresentative":"林成","capital":"8万人民币","businessScope":"建材、钢材、木材、水泥、日杂、农副产品、土特产、销售。","province":"海南","city":"省直辖县","address":"文昌市铺前镇昌华路"},{"name":"文昌市铺前供销社三综合门市部","code":"914690057931350354","registrationDay":"1989-12-11","character":"私营企业","legalRepresentative":"邓文能","capital":"3.2万人民币","businessScope":"日用百货、纺织品、针棉织品、家用电器、日杂、烟。","province":"海南","city":"省直辖县","address":"文昌市铺前镇昌华路5号"},{"name":"文昌市铺前供销社机械门市部","code":"91469005793134999J","registrationDay":"1989-12-11","character":"私营企业","legalRepresentative":"邢忠文","capital":"1.5万人民币","businessScope":"五交电、机械机电零件、钢材、煤油、化工。","province":"海南","city":"省直辖县","address":"文昌市铺前镇昌华路"},{"name":"文昌市铺前供销社针织门市部","code":"914690057931349640","registrationDay":"1989-12-11","character":"私营企业","legalRepresentative":"叶青","capital":"3.4万人民币","businessScope":"针棉织品、日用百货、家用电器、日用土杂、家具、五交化、燃气、燃气炉具。","province":"海南","city":"省直辖县","address":"文昌市铺前镇昌华路"},{"name":"琼中黎族苗族自治县营根供销社","code":"91469036201720370J","registrationDay":"1989-12-12","character":"集体所有制","legalRepresentative":"王明州","capital":"27.5万人民币","businessScope":"农副产品、农业生产资料、日用工业品、五交电、化工、百货、针织、纱布、日用杂品。","province":"海南","city":"省直辖县","address":"琼中县营根镇供销大厦对面"},{"name":"文昌市会文供销社会文贸易综合二门市","code":"91469005MA5RG8C22K","registrationDay":"1989-12-12","character":"私营企业","legalRepresentative":"王忠","capital":"1.5万人民币","businessScope":"五交电、机电产品","province":"海南","city":"省直辖县","address":"会文镇"},{"name":"万宁市牛漏供销合作社","code":"91469006201488321J","registrationDay":"1989-12-14","character":"集体所有制","legalRepresentative":"田万和","capital":"44万人民币","businessScope":"农业生产资料、五交化、百货、日杂、预包装食品兼散装食品、土产、糖烟酒、建材、图书、文具、饲料、大米、纺织品批发、零售。","province":"海南","city":"省直辖县","address":"万宁市长丰镇牛漏墟"},{"name":"万宁市北坡供销合作社","code":"91469006201488284C","registrationDay":"1989-12-14","character":"集体所有制","legalRepresentative":"叶经锋","capital":"35万人民币","businessScope":"农业生产资料","province":"海南","city":"省直辖县","address":"万宁市北坡镇"},{"name":"澄迈县中兴供销社综合三门市部","code":"91469027MA5RFNDF0R","registrationDay":"1989-12-16","character":"集体分支机构(非法人)","legalRepresentative":"王秦丁","capital":"N/A","businessScope":"零售预包装食品、兼散装食品、乳制品","province":"海南","city":"省直辖县","address":"澄迈县中兴圩"},{"name":"文昌市会文供销社第一烟酒门市","code":"91469005MA5RG85L3H","registrationDay":"1989-12-16","character":"私营企业","legalRepresentative":"陈爱珍","capital":"1万人民币","businessScope":"预包装食品、乳制品","province":"海南","city":"省直辖县","address":"会文镇"},{"name":"澄迈县中兴供销社和岭门市部","code":"91469027MA5RFNBG62","registrationDay":"1989-12-16","character":"集体分支机构(非法人)","legalRepresentative":"张凤连","capital":"N/A","businessScope":"日杂、五金、交电","province":"海南","city":"省直辖县","address":"澄迈县中兴圩兴隆街"},{"name":"澄迈县中兴供销社纱布门市部","code":"91469027MA5RFNDE2Y","registrationDay":"1989-12-16","character":"集体分支机构(非法人)","legalRepresentative":"王富亚","capital":"N/A","businessScope":"百货、纱布、文具、五金。","province":"海南","city":"省直辖县","address":"澄迈县中兴圩"},{"name":"文昌市会文供销社会文副食门市","code":"91469005793117152H","registrationDay":"1989-12-16","character":"私营企业","legalRepresentative":"王纪琴","capital":"0.8万人民币","businessScope":"预包装食品兼散装食品、乳制品","province":"海南","city":"省直辖县","address":"会文镇"},{"name":"海南海汽运输集团股份有限公司定安分公司","code":"91469025201500431L","registrationDay":"1989-12-16","character":"N/A","legalRepresentative":"文海川","capital":"N/A","businessScope":"客运、汽车修理、汽车快递服务。","province":"海南","city":"省直辖县","address":"海南省定安县定城镇见龙大道178号"},{"name":"文昌市会文供销社会文综合三门市","code":"91469005324210207U","registrationDay":"1989-12-16","character":"私营企业","legalRepresentative":"邢月花","capital":"0.8万人民币","businessScope":"烟花炮竹，预包装食品散装食品、乳制品，烟、百货、针织、土日杂。","province":"海南","city":"省直辖县","address":"会文镇"},{"name":"文昌市会文供销社文医综合第四门市","code":"9146900576039214XA","registrationDay":"1989-12-16","character":"私营企业","legalRepresentative":"林丽","capital":"1万人民币","businessScope":"中西成药、西药制剂、烟、小百货、日杂、五金交电、预包装食品散装食品，保健食品。","province":"海南","city":"省直辖县","address":"会文镇"},{"name":"文昌市会文供销社化工门市","code":"91469005MA5RG8AC1F","registrationDay":"1989-12-16","character":"私营企业","legalRepresentative":"沈照东","capital":"1万人民币","businessScope":"化工、柴油、煤油。","province":"海南","city":"省直辖县","address":"会文镇"},{"name":"临高县波莲供销社","code":"9146902820156518XD","registrationDay":"1989-12-18","character":"集体所有制","legalRepresentative":"刘招平","capital":"30万人民币","businessScope":"化学肥料、农膜、农具、润滑油、文化用品、建筑材料、新鲜蔬菜运销","province":"海南","city":"省直辖县","address":"海南省临高县波莲镇"},{"name":"三亚市供销社联合总公司","code":"91460200428738890E","registrationDay":"1989-12-22","character":"集体所有制","legalRepresentative":"符史东","capital":"655万人民币","businessScope":"农用生产资料、日用工业品、五金交电、针纺织品、日用百货、家用电器、文化用品、化工原料、果菜副食品、水产品、畜产品、矿产品、林产品、建筑材料、水泥。","province":"海南","city":"三亚","address":"三亚市解放一路"},{"name":"文昌市清澜供销社针百综合门市","code":"91469005MA5RG15G3T","registrationDay":"1989-12-25","character":"私营企业","legalRepresentative":"张春静","capital":"3万人民币","businessScope":"针棉织品、百货、五金交电、日杂、国产卷烟。","province":"海南","city":"省直辖县","address":"文昌市清澜镇"},{"name":"文昌市昌洒供销社五金门市部","code":"914690057931151813","registrationDay":"1989-12-29","character":"集体所有制","legalRepresentative":"伍书款","capital":"1.6万人民币","businessScope":"五金交电、化工、日杂、煤油、销售。","province":"海南","city":"省直辖县","address":"文昌市昌洒镇"},{"name":"文昌市昌洒供销社五金综合门市部","code":"91469005793115202K","registrationDay":"1989-12-29","character":"集体所有制","legalRepresentative":"邢益晓","capital":"2万人民币","businessScope":"五金交电、化工、日杂、煤油、销售。","province":"海南","city":"省直辖县","address":"文昌市昌洒镇"},{"name":"广东省电白建筑集团有限公司海南分公司","code":"91460000742570918B","registrationDay":"1989-12-29","character":"N/A","legalRepresentative":"钟庆生","capital":"N/A","businessScope":"可承担30层以下的房屋建筑一级总承包：公路、桥梁、市政工程、水利工程；水电安装；建筑材料；打桩工程；装饰工程。","province":"海南","city":"海口","address":"海口市五指山路12号福隆大厦A座1001、1101"},{"name":"文昌市东郊供销社丁兰百货综合商行","code":"91469005MA5RG84J0G","registrationDay":"1989-12-30","character":"私营企业","legalRepresentative":"丁兰","capital":"2万人民币","businessScope":"针棉织品、百货用品、文具、家用电器、炉具、服装、鞋帽、五交化、陶瓷器、家具用具、儿童用品、床垫、床上用品。","province":"海南","city":"省直辖县","address":"文昌市东郊镇"}]}